[{"gamma_target": 1.5, "gamma_achieved": 1.475, "pv_used": 1.1767, "n_tasks": 20, "seed": 3, "duration": 2.0, "end_anchor": false, "scenario": "solar", "premium": 0.0, "commit": "a6af645", "milp_solver": "gurobi", "soc_step": 0.25, "pool_own": 98, "pool_union": 167, "pool_harvest": 126, "cg_converged": true, "cg_term": "priced_out", "cg_iters": 28, "cg_s": 0.51, "lp_own": 7962.0929, "lp_artificial_mass": 0.0, "lp_union": 7962.0929, "lp_check_ok": true, "start_src": null, "start_obj": null, "chg_units": 54.0, "dis_units": 0.0, "chg_in_surplus_units": 28.0, "milp_s": 0.09, "milp_status": "optimal", "solver_bound": 8016.35, "artificials": 0, "feasible": true, "outcome": "feasible", "total": 8016.35, "g_units": 192.5, "trucks": 7, "batteries": 0}, {"gamma_target": 1.5, "gamma_achieved": 1.475, "pv_used": 1.1767, "n_tasks": 20, "seed": 3, "duration": 2.0, "end_anchor": false, "scenario": "solar_bess", "premium": 0.0, "commit": "a6af645", "milp_solver": "gurobi", "soc_step": 0.25, "pool_own": 105, "pool_union": 167, "pool_harvest": 126, "cg_converged": true, "cg_term": "priced_out", "cg_iters": 35, "cg_s": 0.67, "lp_own": 6813.8107, "lp_artificial_mass": 0.0, "lp_union": 6813.8107, "lp_check_ok": true, "start_src": "solar@0", "start_obj": 8016.35, "chg_units": 95.25, "dis_units": 0.0, "chg_in_surplus_units": 59.0, "milp_s": 0.05, "milp_status": "optimal", "solver_bound": 6830.525, "artificials": 0, "feasible": true, "outcome": "feasible", "total": 6830.52, "g_units": 156.5, "trucks": 7, "batteries": 7}, {"gamma_target": 1.5, "gamma_achieved": 1.475, "pv_used": 1.1767, "n_tasks": 20, "seed": 3, "duration": 2.0, "end_anchor": false, "scenario": "v2g_fleet", "premium": 0.0, "commit": "a6af645", "milp_solver": "gurobi", "soc_step": 0.25, "pool_own": 212, "pool_union": 420, "pool_harvest": 126, "cg_converged": true, "cg_term": "priced_out", "cg_iters": 142, "cg_s": 2.32, "lp_own": 6793.5482, "lp_artificial_mass": 0.0, "lp_union": 6793.5482, "lp_check_ok": true, "start_src": "solar_bess@0", "start_obj": 6830.52, "chg_units": 99.5, "dis_units": 0.0, "chg_in_surplus_units": 68.25, "milp_s": 4.27, "milp_status": "optimal", "solver_bound": 6938.65, "artificials": 0, "feasible": true, "outcome": "feasible", "total": 6938.65, "g_units": 163.25, "trucks": 9, "batteries": 0}, {"gamma_target": 1.5, "gamma_achieved": 1.475, "pv_used": 1.1767, "n_tasks": 20, "seed": 3, "duration": 2.0, "end_anchor": false, "scenario": "v2g", "premium": 0.0, "commit": "a6af645", "milp_solver": "gurobi", "soc_step": 0.25, "pool_own": 101, "pool_union": 420, "pool_harvest": 126, "cg_converged": true, "cg_term": "priced_out", "cg_iters": 31, "cg_s": 0.72, "lp_own": 6766.9411, "lp_artificial_mass": 0.0, "lp_union": 6766.9411, "lp_check_ok": true, "start_src": "solar_bess@0", "start_obj": 6830.52, "chg_units": 95.25, "dis_units": 0.0, "chg_in_surplus_units": 61.5, "milp_s": 0.15, "milp_status": "optimal", "solver_bound": 6778.400000000001, "artificials": 0, "feasible": true, "outcome": "feasible", "total": 6778.51, "g_units": 157.0, "trucks": 7, "batteries": 5}, {"gamma_target": 1.5, "gamma_achieved": 1.475, "pv_used": 1.1767, "n_tasks": 20, "seed": 3, "duration": 2.0, "end_anchor": false, "scenario": "v2g", "premium": 4.0, "commit": "a6af645", "milp_solver": "gurobi", "soc_step": 0.25, "pool_own": 108, "pool_union": 420, "pool_harvest": 126, "cg_converged": true, "cg_term": "priced_out", "cg_iters": 38, "cg_s": 0.83, "lp_own": 6794.9411, "lp_artificial_mass": 0.0, "lp_union": 6794.9411, "lp_check_ok": true, "start_src": "v2g@0", "start_obj": 6806.51, "chg_units": 95.25, "dis_units": 0.0, "chg_in_surplus_units": 61.5, "milp_s": 0.15, "milp_status": "optimal", "solver_bound": 6806.400000000001, "artificials": 0, "feasible": true, "outcome": "feasible", "total": 6806.51, "g_units": 157.0, "trucks": 7, "batteries": 5}, {"gamma_target": 1.5, "gamma_achieved": 1.475, "pv_used": 1.1767, "n_tasks": 20, "seed": 3, "duration": 2.0, "end_anchor": false, "scenario": "v2g", "premium": 8.0, "commit": "a6af645", "milp_solver": "gurobi", "soc_step": 0.25, "pool_own": 108, "pool_union": 420, "pool_harvest": 126, "cg_converged": true, "cg_term": "priced_out", "cg_iters": 38, "cg_s": 0.84, "lp_own": 6822.9411, "lp_artificial_mass": 0.0, "lp_union": 6822.9411, "lp_check_ok": true, "start_src": "v2g@0", "start_obj": 6834.51, "chg_units": 95.25, "dis_units": 0.0, "chg_in_surplus_units": 61.5, "milp_s": 0.15, "milp_status": "optimal", "solver_bound": 6834.400000000001, "artificials": 0, "feasible": true, "outcome": "feasible", "total": 6834.51, "g_units": 157.0, "trucks": 7, "batteries": 5}, {"gamma_target": 0.5, "gamma_achieved": 0.475, "pv_used": 0.8234, "n_tasks": 20, "seed": 4, "duration": 2.0, "end_anchor": false, "scenario": "solar", "premium": 0.0, "commit": "a6af645", "milp_solver": "gurobi", "soc_step": 0.25, "pool_own": 118, "pool_union": 215, "pool_harvest": 233, "cg_converged": true, "cg_term": "priced_out", "cg_iters": 48, "cg_s": 0.71, "lp_own": 8791.2667, "lp_artificial_mass": 0.0, "lp_union": 8791.2667, "lp_check_ok": true, "start_src": null, "start_obj": null, "chg_units": 50.0, "dis_units": 0.0, "chg_in_surplus_units": 18.0, "milp_s": 0.08, "milp_status": "optimal", "solver_bound": 8811.25, "artificials": 0, "feasible": true, "outcome": "feasible", "total": 8811.25, "g_units": 211.25, "trucks": 8, "batteries": 0}, {"gamma_target": 0.5, "gamma_achieved": 0.475, "pv_used": 0.8234, "n_tasks": 20, "seed": 4, "duration": 2.0, "end_anchor": false, "scenario": "solar_bess", "premium": 0.0, "commit": "a6af645", "milp_solver": "gurobi", "soc_step": 0.25, "pool_own": 113, "pool_union": 215, "pool_harvest": 233, "cg_converged": true, "cg_term": "priced_out", "cg_iters": 43, "cg_s": 0.85, "lp_own": 8644.4589, "lp_artificial_mass": 0.0, "lp_union": 8644.4589, "lp_check_ok": true, "start_src": "solar@0", "start_obj": 8811.25, "chg_units": 61.75, "dis_units": 0.0, "chg_in_surplus_units": 19.0, "milp_s": 0.06, "milp_status": "optimal", "solver_bound": 8659.8875, "artificials": 0, "feasible": true, "outcome": "feasible", "total": 8659.89, "g_units": 207.0, "trucks": 6, "batteries": 3}, {"gamma_target": 0.5, "gamma_achieved": 0.475, "pv_used": 0.8234, "n_tasks": 20, "seed": 4, "duration": 2.0, "end_anchor": false, "scenario": "v2g_fleet", "premium": 0.0, "commit": "a6af645", "milp_solver": "gurobi", "soc_step": 0.25, "pool_own": 125, "pool_union": 309, "pool_harvest": 233, "cg_converged": true, "cg_term": "priced_out", "cg_iters": 55, "cg_s": 0.94, "lp_own": 8684.6077, "lp_artificial_mass": 0.0, "lp_union": 8684.6077, "lp_check_ok": true, "start_src": "solar_bess@0", "start_obj": 8659.89, "chg_units": 63.0, "dis_units": 0.0, "chg_in_surplus_units": 21.0, "milp_s": 0.2, "milp_status": "optimal", "solver_bound": 8711.737500000001, "artificials": 0, "feasible": true, "outcome": "feasible", "total": 8711.94, "g_units": 208.75, "trucks": 8, "batteries": 0}, {"gamma_target": 0.5, "gamma_achieved": 0.475, "pv_used": 0.8234, "n_tasks": 20, "seed": 4, "duration": 2.0, "end_anchor": false, "scenario": "v2g", "premium": 0.0, "commit": "a6af645", "milp_solver": "gurobi", "soc_step": 0.25, "pool_own": 112, "pool_union": 309, "pool_harvest": 233, "cg_converged": true, "cg_term": "priced_out", "cg_iters": 42, "cg_s": 0.95, "lp_own": 8644.4589, "lp_artificial_mass": 0.0, "lp_union": 8644.4589, "lp_check_ok": true, "start_src": "solar_bess@0", "start_obj": 8659.89, "chg_units": 61.75, "dis_units": 0.0, "chg_in_surplus_units": 19.0, "milp_s": 0.11, "milp_status": "optimal", "solver_bound": 8659.8875, "artificials": 0, "feasible": true, "outcome": "feasible", "total": 8659.89, "g_units": 207.0, "trucks": 6, "batteries": 3}, {"gamma_target": 0.5, "gamma_achieved": 0.475, "pv_used": 0.8234, "n_tasks": 20, "seed": 4, "duration": 2.0, "end_anchor": false, "scenario": "v2g", "premium": 4.0, "commit": "a6af645", "milp_solver": "gurobi", "soc_step": 0.25, "pool_own": 112, "pool_union": 309, "pool_harvest": 233, "cg_converged": true, "cg_term": "priced_out", "cg_iters": 42, "cg_s": 0.93, "lp_own": 8668.4589, "lp_artificial_mass": 0.0, "lp_union": 8668.4589, "lp_check_ok": true, "start_src": "solar_bess@0", "start_obj": 8683.89, "chg_units": 61.75, "dis_units": 0.0, "chg_in_surplus_units": 19.0, "milp_s": 0.11, "milp_status": "optimal", "solver_bound": 8683.8875, "artificials": 0, "feasible": true, "outcome": "feasible", "total": 8683.89, "g_units": 207.0, "trucks": 6, "batteries": 3}, {"gamma_target": 0.5, "gamma_achieved": 0.475, "pv_used": 0.8234, "n_tasks": 20, "seed": 4, "duration": 2.0, "end_anchor": false, "scenario": "v2g", "premium": 8.0, "commit": "a6af645", "milp_solver": "gurobi", "soc_step": 0.25, "pool_own": 109, "pool_union": 309, "pool_harvest": 233, "cg_converged": true, "cg_term": "priced_out", "cg_iters": 39, "cg_s": 0.87, "lp_own": 8692.4589, "lp_artificial_mass": 0.0, "lp_union": 8692.4589, "lp_check_ok": true, "start_src": "solar_bess@0", "start_obj": 8707.89, "chg_units": 61.75, "dis_units": 0.0, "chg_in_surplus_units": 19.0, "milp_s": 0.09, "milp_status": "optimal", "solver_bound": 8707.8875, "artificials": 0, "feasible": true, "outcome": "feasible", "total": 8707.89, "g_units": 207.0, "trucks": 6, "batteries": 3}, {"gamma_target": 1.0, "gamma_achieved": 1.0, "pv_used": 2.5217, "n_tasks": 120, "seed": 4, "duration": 2.0, "end_anchor": false, "scenario": "solar", "premium": 0.0, "commit": "a6af645", "milp_solver": "gurobi", "soc_step": 0.25, "pool_own": 558, "pool_union": 1399, "pool_harvest": 1190, "cg_converged": true, "cg_term": "priced_out", "cg_iters": 269, "cg_s": 4.32, "lp_own": 12352.881, "lp_artificial_mass": 0.0, "lp_union": 12352.881, "lp_check_ok": true, "start_src": null, "start_obj": null, "chg_units": 313.0, "dis_units": 0.0, "chg_in_surplus_units": 192.25, "milp_s": 600.56, "milp_status": "feasible", "solver_bound": 12429.302157037551, "artificials": 0, "feasible": true, "outcome": "feasible", "total": 12552.83, "g_units": 276.5, "trucks": 33, "batteries": 0}, {"gamma_target": 1.0, "gamma_achieved": 1.0, "pv_used": 2.5217, "n_tasks": 120, "seed": 4, "duration": 2.0, "end_anchor": false, "scenario": "solar_bess", "premium": 0.0, "commit": "a6af645", "milp_solver": "gurobi", "soc_step": 0.25, "pool_own": 578, "pool_union": 1399, "pool_harvest": 1190, "cg_converged": true, "cg_term": "priced_out", "cg_iters": 289, "cg_s": 10.06, "lp_own": 9673.372, "lp_artificial_mass": 0.0, "lp_union": 9673.372, "lp_check_ok": true, "start_src": "solar@0", "start_obj": 12552.83, "chg_units": 407.5, "dis_units": 0.0, "chg_in_surplus_units": 251.75, "milp_s": 600.44, "milp_status": "feasible", "solver_bound": 9680.20837980259, "artificials": 0, "feasible": true, "outcome": "feasible", "total": 9760.22, "g_units": 195.75, "trucks": 29, "batteries": 17}, {"gamma_target": 1.0, "gamma_achieved": 1.0, "pv_used": 2.5217, "n_tasks": 120, "seed": 4, "duration": 2.0, "end_anchor": false, "scenario": "v2g_fleet", "premium": 0.0, "commit": "a6af645", "milp_solver": "gurobi", "soc_step": 0.25, "pool_own": 1011, "pool_union": 2544, "pool_harvest": 1190, "cg_converged": true, "cg_term": "priced_out", "cg_iters": 722, "cg_s": 30.01, "lp_own": 9995.7488, "lp_artificial_mass": 0.0, "lp_union": 9995.7488, "lp_check_ok": true, "start_src": "solar_bess@0", "start_obj": 9760.22, "chg_units": 405.25, "dis_units": 0.0, "chg_in_surplus_units": 249.25, "milp_s": 600.49, "milp_status": "feasible", "solver_bound": 10172.36259925795, "artificials": 0, "feasible": true, "outcome": "feasible", "total": 10672.76, "g_units": 223.75, "trucks": 38, "batteries": 0}, {"gamma_target": 1.0, "gamma_achieved": 1.0, "pv_used": 2.5217, "n_tasks": 120, "seed": 4, "duration": 2.0, "end_anchor": false, "scenario": "v2g", "premium": 0.0, "commit": "a6af645", "milp_solver": "gurobi", "soc_step": 0.25, "pool_own": 608, "pool_union": 2544, "pool_harvest": 1190, "cg_converged": true, "cg_term": "priced_out", "cg_iters": 319, "cg_s": 12.91, "lp_own": 9441.9401, "lp_artificial_mass": 0.0, "lp_union": 9441.9401, "lp_check_ok": true, "start_src": "solar_bess@0", "start_obj": 9760.22, "chg_units": 405.0, "dis_units": 0.0, "chg_in_surplus_units": 246.25, "milp_s": 600.35, "milp_status": "feasible", "solver_bound": 9451.480086233565, "artificials": 0, "feasible": true, "outcome": "feasible", "total": 9461.15, "g_units": 193.0, "trucks": 32, "batteries": 8}, {"gamma_target": 1.0, "gamma_achieved": 1.0, "pv_used": 2.5217, "n_tasks": 120, "seed": 4, "duration": 2.0, "end_anchor": false, "scenario": "v2g", "premium": 4.0, "commit": "a6af645", "milp_solver": "gurobi", "soc_step": 0.25, "pool_own": 609, "pool_union": 2544, "pool_harvest": 1190, "cg_converged": true, "cg_term": "priced_out", "cg_iters": 320, "cg_s": 12.29, "lp_own": 9574.4868, "lp_artificial_mass": 0.0, "lp_union": 9574.4868, "lp_check_ok": true, "start_src": "v2g@0", "start_obj": 9589.15, "chg_units": 405.0, "dis_units": 0.0, "chg_in_surplus_units": 246.25, "milp_s": 600.41, "milp_status": "feasible", "solver_bound": 9581.900050479955, "artificials": 0, "feasible": true, "outcome": "feasible", "total": 9589.15, "g_units": 193.0, "trucks": 32, "batteries": 8}, {"gamma_target": 1.0, "gamma_achieved": 1.0, "pv_used": 2.5217, "n_tasks": 120, "seed": 4, "duration": 2.0, "end_anchor": false, "scenario": "v2g", "premium": 8.0, "commit": "a6af645", "milp_solver": "gurobi", "soc_step": 0.25, "pool_own": 620, "pool_union": 2544, "pool_harvest": 1190, "cg_converged": true, "cg_term": "priced_out", "cg_iters": 331, "cg_s": 13.52, "lp_own": 9706.3977, "lp_artificial_mass": 0.0, "lp_union": 9706.3977, "lp_check_ok": true, "start_src": "v2g@4", "start_obj": 9717.15, "chg_units": 405.0, "dis_units": 0.0, "chg_in_surplus_units": 246.25, "milp_s": 600.43, "milp_status": "feasible", "solver_bound": 9714.573375526916, "artificials": 0, "feasible": true, "outcome": "feasible", "total": 9717.15, "g_units": 193.0, "trucks": 32, "batteries": 8}, {"gamma_target": 2.0, "gamma_achieved": 2.0, "pv_used": 2.5217, "n_tasks": 60, "seed": 5, "duration": 2.0, "end_anchor": false, "scenario": "solar", "premium": 0.0, "commit": "a6af645", "milp_solver": "gurobi", "soc_step": 0.25, "pool_own": 267, "pool_union": 553, "pool_harvest": 455, "cg_converged": true, "cg_term": "priced_out", "cg_iters": 107, "cg_s": 0.99, "lp_own": 10040.95, "lp_artificial_mass": 0.0, "lp_union": 10040.95, "lp_check_ok": true, "start_src": null, "start_obj": null, "chg_units": 161.0, "dis_units": 0.0, "chg_in_surplus_units": 81.75, "milp_s": 0.3, "milp_status": "optimal", "solver_bound": 10053.982661290323, "artificials": 0, "feasible": true, "outcome": "feasible", "total": 10054.02, "g_units": 228.75, "trucks": 20, "batteries": 0}, {"gamma_target": 2.0, "gamma_achieved": 2.0, "pv_used": 2.5217, "n_tasks": 60, "seed": 5, "duration": 2.0, "end_anchor": false, "scenario": "solar_bess", "premium": 0.0, "commit": "a6af645", "milp_solver": "gurobi", "soc_step": 0.25, "pool_own": 302, "pool_union": 553, "pool_harvest": 455, "cg_converged": true, "cg_term": "priced_out", "cg_iters": 142, "cg_s": 2.32, "lp_own": 3914.4107, "lp_artificial_mass": 0.0, "lp_union": 3914.4107, "lp_check_ok": true, "start_src": "solar@0", "start_obj": 10054.02, "chg_units": 351.0, "dis_units": 0.0, "chg_in_surplus_units": 240.0, "milp_s": 1.46, "milp_status": "optimal", "solver_bound": 3938.975, "artificials": 0, "feasible": true, "outcome": "feasible", "total": 3938.98, "g_units": 52.0, "trucks": 17, "batteries": 30}, {"gamma_target": 2.0, "gamma_achieved": 2.0, "pv_used": 2.5217, "n_tasks": 60, "seed": 5, "duration": 2.0, "end_anchor": false, "scenario": "v2g_fleet", "premium": 0.0, "commit": "a6af645", "milp_solver": "gurobi", "soc_step": 0.25, "pool_own": 504, "pool_union": 1267, "pool_harvest": 455, "cg_converged": true, "cg_term": "priced_out", "cg_iters": 344, "cg_s": 5.98, "lp_own": 7244.45, "lp_artificial_mass": 0.0, "lp_union": 7244.45, "lp_check_ok": true, "start_src": "solar_bess@0", "start_obj": 3938.98, "chg_units": 262.25, "dis_units": 0.0, "chg_in_surplus_units": 164.5, "milp_s": 600.63, "milp_status": "feasible", "solver_bound": 7261.229512728706, "artificials": 0, "feasible": true, "outcome": "feasible", "total": 7419.16, "g_units": 160.5, "trucks": 22, "batteries": 0}, {"gamma_target": 2.0, "gamma_achieved": 2.0, "pv_used": 2.5217, "n_tasks": 60, "seed": 5, "duration": 2.0, "end_anchor": false, "scenario": "v2g", "premium": 0.0, "commit": "a6af645", "milp_solver": "gurobi", "soc_step": 0.25, "pool_own": 311, "pool_union": 1267, "pool_harvest": 455, "cg_converged": true, "cg_term": "priced_out", "cg_iters": 151, "cg_s": 2.79, "lp_own": 3653.8446, "lp_artificial_mass": 0.0, "lp_union": 3653.8446, "lp_check_ok": true, "start_src": "solar_bess@0", "start_obj": 3938.98, "chg_units": 349.75, "dis_units": 0.0, "chg_in_surplus_units": 240.5, "milp_s": 30.4, "milp_status": "optimal", "solver_bound": 3665.937452777606, "artificials": 0, "feasible": true, "outcome": "feasible", "total": 3665.94, "g_units": 51.25, "trucks": 18, "batteries": 22}, {"gamma_target": 2.0, "gamma_achieved": 2.0, "pv_used": 2.5217, "n_tasks": 60, "seed": 5, "duration": 2.0, "end_anchor": false, "scenario": "v2g", "premium": 4.0, "commit": "a6af645", "milp_solver": "gurobi", "soc_step": 0.25, "pool_own": 316, "pool_union": 1267, "pool_harvest": 455, "cg_converged": true, "cg_term": "priced_out", "cg_iters": 156, "cg_s": 2.92, "lp_own": 3723.5589, "lp_artificial_mass": 0.0, "lp_union": 3723.5589, "lp_check_ok": true, "start_src": "v2g@0", "start_obj": 3737.94, "chg_units": 349.75, "dis_units": 0.0, "chg_in_surplus_units": 240.5, "milp_s": 44.0, "milp_status": "optimal", "solver_bound": 3737.937454158799, "artificials": 0, "feasible": true, "outcome": "feasible", "total": 3737.94, "g_units": 51.25, "trucks": 18, "batteries": 22}, {"gamma_target": 2.0, "gamma_achieved": 2.0, "pv_used": 2.5217, "n_tasks": 60, "seed": 5, "duration": 2.0, "end_anchor": false, "scenario": "v2g", "premium": 8.0, "commit": "a6af645", "milp_solver": "gurobi", "soc_step": 0.25, "pool_own": 324, "pool_union": 1267, "pool_harvest": 455, "cg_converged": true, "cg_term": "priced_out", "cg_iters": 164, "cg_s": 3.2, "lp_own": 3793.0375, "lp_artificial_mass": 0.0, "lp_union": 3793.0375, "lp_check_ok": true, "start_src": "v2g@0", "start_obj": 3809.94, "chg_units": 349.75, "dis_units": 0.0, "chg_in_surplus_units": 240.5, "milp_s": 600.56, "milp_status": "feasible", "solver_bound": 3802.1097326615313, "artificials": 0, "feasible": true, "outcome": "feasible", "total": 3809.94, "g_units": 51.25, "trucks": 18, "batteries": 22}, {"gamma_target": 0.75, "gamma_achieved": 0.7417, "pv_used": 1.4129, "n_tasks": 60, "seed": 6, "duration": 2.0, "end_anchor": false, "scenario": "solar", "premium": 0.0, "commit": "a6af645", "milp_solver": "gurobi", "soc_step": 0.25, "pool_own": 298, "pool_union": 781, "pool_harvest": 691, "cg_converged": true, "cg_term": "priced_out", "cg_iters": 141, "cg_s": 1.31, "lp_own": 10198.9429, "lp_artificial_mass": 0.0, "lp_union": 10198.9429, "lp_check_ok": true, "start_src": null, "start_obj": null, "chg_units": 155.0, "dis_units": 0.0, "chg_in_surplus_units": 85.75, "milp_s": 5.51, "milp_status": "optimal", "solver_bound": 10328.875, "artificials": 0, "feasible": true, "outcome": "feasible", "total": 10328.88, "g_units": 236.75, "trucks": 19, "batteries": 0}, {"gamma_target": 0.75, "gamma_achieved": 0.7417, "pv_used": 1.4129, "n_tasks": 60, "seed": 6, "duration": 2.0, "end_anchor": false, "scenario": "solar_bess", "premium": 0.0, "commit": "a6af645", "milp_solver": "gurobi", "soc_step": 0.25, "pool_own": 290, "pool_union": 781, "pool_harvest": 691, "cg_converged": true, "cg_term": "priced_out", "cg_iters": 133, "cg_s": 1.79, "lp_own": 9663.649, "lp_artificial_mass": 0.0, "lp_union": 9663.649, "lp_check_ok": true, "start_src": "solar@0", "start_obj": 10328.88, "chg_units": 192.5, "dis_units": 0.0, "chg_in_surplus_units": 94.25, "milp_s": 0.75, "milp_status": "optimal", "solver_bound": 9678.0375, "artificials": 0, "feasible": true, "outcome": "feasible", "total": 9678.04, "g_units": 217.5, "trucks": 16, "batteries": 7}, {"gamma_target": 0.75, "gamma_achieved": 0.7417, "pv_used": 1.4129, "n_tasks": 60, "seed": 6, "duration": 2.0, "end_anchor": false, "scenario": "v2g_fleet", "premium": 0.0, "commit": "a6af645", "milp_solver": "gurobi", "soc_step": 0.25, "pool_own": 501, "pool_union": 1208, "pool_harvest": 691, "cg_converged": true, "cg_term": "priced_out", "cg_iters": 344, "cg_s": 5.05, "lp_own": 9630.3982, "lp_artificial_mass": 0.0, "lp_union": 9630.3982, "lp_check_ok": true, "start_src": "solar_bess@0", "start_obj": 9678.04, "chg_units": 235.5, "dis_units": 0.0, "chg_in_surplus_units": 106.5, "milp_s": 190.5, "milp_status": "optimal", "solver_bound": 9703.175, "artificials": 0, "feasible": true, "outcome": "feasible", "total": 9703.17, "g_units": 218.75, "trucks": 21, "batteries": 0}, {"gamma_target": 0.75, "gamma_achieved": 0.7417, "pv_used": 1.4129, "n_tasks": 60, "seed": 6, "duration": 2.0, "end_anchor": false, "scenario": "v2g", "premium": 0.0, "commit": "a6af645", "milp_solver": "gurobi", "soc_step": 0.25, "pool_own": 311, "pool_union": 1208, "pool_harvest": 691, "cg_converged": true, "cg_term": "priced_out", "cg_iters": 154, "cg_s": 2.33, "lp_own": 9596.3286, "lp_artificial_mass": 0.0, "lp_union": 9596.3286, "lp_check_ok": true, "start_src": "solar_bess@0", "start_obj": 9678.04, "chg_units": 196.5, "dis_units": 0.0, "chg_in_surplus_units": 98.5, "milp_s": 0.58, "milp_status": "optimal", "solver_bound": 9620.112499999997, "artificials": 0, "feasible": true, "outcome": "feasible", "total": 9620.26, "g_units": 216.5, "trucks": 18, "batteries": 4}, {"gamma_target": 0.75, "gamma_achieved": 0.7417, "pv_used": 1.4129, "n_tasks": 60, "seed": 6, "duration": 2.0, "end_anchor": false, "scenario": "v2g", "premium": 4.0, "commit": "a6af645", "milp_solver": "gurobi", "soc_step": 0.25, "pool_own": 304, "pool_union": 1208, "pool_harvest": 691, "cg_converged": true, "cg_term": "priced_out", "cg_iters": 147, "cg_s": 2.24, "lp_own": 9665.1286, "lp_artificial_mass": 0.0, "lp_union": 9665.1286, "lp_check_ok": true, "start_src": "v2g@0", "start_obj": 9692.26, "chg_units": 196.5, "dis_units": 0.0, "chg_in_surplus_units": 98.5, "milp_s": 0.42, "milp_status": "optimal", "solver_bound": 9692.112500000003, "artificials": 0, "feasible": true, "outcome": "feasible", "total": 9692.26, "g_units": 216.5, "trucks": 18, "batteries": 4}, {"gamma_target": 0.75, "gamma_achieved": 0.7417, "pv_used": 1.4129, "n_tasks": 60, "seed": 6, "duration": 2.0, "end_anchor": false, "scenario": "v2g", "premium": 8.0, "commit": "a6af645", "milp_solver": "gurobi", "soc_step": 0.25, "pool_own": 295, "pool_union": 1208, "pool_harvest": 691, "cg_converged": true, "cg_term": "priced_out", "cg_iters": 138, "cg_s": 2.02, "lp_own": 9732.3348, "lp_artificial_mass": 0.0, "lp_union": 9732.3348, "lp_check_ok": true, "start_src": "v2g@0", "start_obj": 9764.26, "chg_units": 192.75, "dis_units": 0.0, "chg_in_surplus_units": 97.5, "milp_s": 0.47, "milp_status": "optimal", "solver_bound": 9760.9625, "artificials": 0, "feasible": true, "outcome": "feasible", "total": 9761.06, "g_units": 217.75, "trucks": 17, "batteries": 4}, {"gamma_target": 1.5, "gamma_achieved": 1.475, "pv_used": 1.1767, "n_tasks": 20, "seed": 7, "duration": 2.0, "end_anchor": false, "scenario": "solar", "premium": 0.0, "commit": "a6af645", "milp_solver": "gurobi", "soc_step": 0.25, "pool_own": 103, "pool_union": 182, "pool_harvest": 166, "cg_converged": true, "cg_term": "priced_out", "cg_iters": 33, "cg_s": 0.24, "lp_own": 7988.5286, "lp_artificial_mass": 0.0, "lp_union": 7988.5286, "lp_check_ok": true, "start_src": null, "start_obj": null, "chg_units": 55.5, "dis_units": 0.0, "chg_in_surplus_units": 33.25, "milp_s": 0.06, "milp_status": "optimal", "solver_bound": 8021.387499999953, "artificials": 0, "feasible": true, "outcome": "feasible", "total": 8021.39, "g_units": 189.25, "trucks": 10, "batteries": 0}, {"gamma_target": 1.5, "gamma_achieved": 1.475, "pv_used": 1.1767, "n_tasks": 20, "seed": 7, "duration": 2.0, "end_anchor": false, "scenario": "solar_bess", "premium": 0.0, "commit": "a6af645", "milp_solver": "gurobi", "soc_step": 0.25, "pool_own": 101, "pool_union": 182, "pool_harvest": 166, "cg_converged": true, "cg_term": "priced_out", "cg_iters": 31, "cg_s": 0.29, "lp_own": 6896.2929, "lp_artificial_mass": 0.0, "lp_union": 6896.2929, "lp_check_ok": true, "start_src": "solar@0", "start_obj": 8021.39, "chg_units": 97.75, "dis_units": 0.0, "chg_in_surplus_units": 63.75, "milp_s": 0.06, "milp_status": "optimal", "solver_bound": 6910.599999999953, "artificials": 0, "feasible": true, "outcome": "feasible", "total": 6910.6, "g_units": 158.5, "trucks": 7, "batteries": 7}, {"gamma_target": 1.5, "gamma_achieved": 1.475, "pv_used": 1.1767, "n_tasks": 20, "seed": 7, "duration": 2.0, "end_anchor": false, "scenario": "v2g_fleet", "premium": 0.0, "commit": "a6af645", "milp_solver": "gurobi", "soc_step": 0.25, "pool_own": 187, "pool_union": 394, "pool_harvest": 166, "cg_converged": true, "cg_term": "priced_out", "cg_iters": 117, "cg_s": 0.95, "lp_own": 6950.9, "lp_artificial_mass": 0.0, "lp_union": 6950.9, "lp_check_ok": true, "start_src": "solar_bess@0", "start_obj": 6910.6, "chg_units": 92.25, "dis_units": 0.0, "chg_in_surplus_units": 66.75, "milp_s": 2.65, "milp_status": "optimal", "solver_bound": 7043.2875, "artificials": 0, "feasible": true, "outcome": "feasible", "total": 7043.29, "g_units": 162.5, "trucks": 12, "batteries": 0}, {"gamma_target": 1.5, "gamma_achieved": 1.475, "pv_used": 1.1767, "n_tasks": 20, "seed": 7, "duration": 2.0, "end_anchor": false, "scenario": "v2g", "premium": 0.0, "commit": "a6af645", "milp_solver": "gurobi", "soc_step": 0.25, "pool_own": 111, "pool_union": 394, "pool_harvest": 166, "cg_converged": true, "cg_term": "priced_out", "cg_iters": 41, "cg_s": 0.45, "lp_own": 6852.7875, "lp_artificial_mass": 0.0, "lp_union": 6852.7875, "lp_check_ok": true, "start_src": "solar_bess@0", "start_obj": 6910.6, "chg_units": 91.5, "dis_units": 0.0, "chg_in_surplus_units": 60.25, "milp_s": 0.22, "milp_status": "optimal", "solver_bound": 6883.287499999999, "artificials": 0, "feasible": true, "outcome": "feasible", "total": 6883.29, "g_units": 158.5, "trucks": 8, "batteries": 5}, {"gamma_target": 1.5, "gamma_achieved": 1.475, "pv_used": 1.1767, "n_tasks": 20, "seed": 7, "duration": 2.0, "end_anchor": false, "scenario": "v2g", "premium": 4.0, "commit": "a6af645", "milp_solver": "gurobi", "soc_step": 0.25, "pool_own": 110, "pool_union": 394, "pool_harvest": 166, "cg_converged": true, "cg_term": "priced_out", "cg_iters": 40, "cg_s": 0.43, "lp_own": 6885.3589, "lp_artificial_mass": 0.0, "lp_union": 6885.3589, "lp_check_ok": true, "start_src": "v2g@0", "start_obj": 6915.29, "chg_units": 91.5, "dis_units": 0.0, "chg_in_surplus_units": 60.25, "milp_s": 0.27, "milp_status": "optimal", "solver_bound": 6915.2875, "artificials": 0, "feasible": true, "outcome": "feasible", "total": 6915.29, "g_units": 158.5, "trucks": 8, "batteries": 5}, {"gamma_target": 1.5, "gamma_achieved": 1.475, "pv_used": 1.1767, "n_tasks": 20, "seed": 7, "duration": 2.0, "end_anchor": false, "scenario": "v2g", "premium": 8.0, "commit": "a6af645", "milp_solver": "gurobi", "soc_step": 0.25, "pool_own": 114, "pool_union": 394, "pool_harvest": 166, "cg_converged": true, "cg_term": "priced_out", "cg_iters": 44, "cg_s": 0.46, "lp_own": 6917.0987, "lp_artificial_mass": 0.0, "lp_union": 6917.0987, "lp_check_ok": true, "start_src": "v2g@0", "start_obj": 6947.29, "chg_units": 91.5, "dis_units": 0.0, "chg_in_surplus_units": 60.25, "milp_s": 0.3, "milp_status": "optimal", "solver_bound": 6947.2875, "artificials": 0, "feasible": true, "outcome": "feasible", "total": 6947.29, "g_units": 158.5, "trucks": 8, "batteries": 5}, {"gamma_target": 0.5, "gamma_achieved": 0.475, "pv_used": 0.8234, "n_tasks": 20, "seed": 8, "duration": 2.0, "end_anchor": false, "scenario": "solar", "premium": 0.0, "commit": "a6af645", "milp_solver": "gurobi", "soc_step": 0.25, "pool_own": 120, "pool_union": 206, "pool_harvest": 230, "cg_converged": true, "cg_term": "priced_out", "cg_iters": 50, "cg_s": 0.33, "lp_own": 8721.25, "lp_artificial_mass": 0.0, "lp_union": 8721.25, "lp_check_ok": true, "start_src": null, "start_obj": null, "chg_units": 50.0, "dis_units": 0.0, "chg_in_surplus_units": 20.25, "milp_s": 0.1, "milp_status": "optimal", "solver_bound": 8771.25, "artificials": 0, "feasible": true, "outcome": "feasible", "total": 8771.25, "g_units": 210.25, "trucks": 8, "batteries": 0}, {"gamma_target": 0.5, "gamma_achieved": 0.475, "pv_used": 0.8234, "n_tasks": 20, "seed": 8, "duration": 2.0, "end_anchor": false, "scenario": "solar_bess", "premium": 0.0, "commit": "a6af645", "milp_solver": "gurobi", "soc_step": 0.25, "pool_own": 109, "pool_union": 206, "pool_harvest": 230, "cg_converged": true, "cg_term": "priced_out", "cg_iters": 39, "cg_s": 0.37, "lp_own": 8629.1387, "lp_artificial_mass": 0.0, "lp_union": 8629.1387, "lp_check_ok": true, "start_src": "solar@0", "start_obj": 8771.25, "chg_units": 60.25, "dis_units": 0.0, "chg_in_surplus_units": 20.5, "milp_s": 0.04, "milp_status": "optimal", "solver_bound": 8643.8, "artificials": 0, "feasible": true, "outcome": "feasible", "total": 8643.8, "g_units": 207.5, "trucks": 6, "batteries": 2}, {"gamma_target": 0.5, "gamma_achieved": 0.475, "pv_used": 0.8234, "n_tasks": 20, "seed": 8, "duration": 2.0, "end_anchor": false, "scenario": "v2g_fleet", "premium": 0.0, "commit": "a6af645", "milp_solver": "gurobi", "soc_step": 0.25, "pool_own": 135, "pool_union": 288, "pool_harvest": 230, "cg_converged": true, "cg_term": "priced_out", "cg_iters": 65, "cg_s": 0.49, "lp_own": 8643.0339, "lp_artificial_mass": 0.0, "lp_union": 8643.0339, "lp_check_ok": true, "start_src": "solar_bess@0", "start_obj": 8643.8, "chg_units": 59.5, "dis_units": 0.0, "chg_in_surplus_units": 22.75, "milp_s": 0.1, "milp_status": "optimal", "solver_bound": 8681.7625, "artificials": 0, "feasible": true, "outcome": "feasible", "total": 8681.76, "g_units": 208.0, "trucks": 8, "batteries": 0}, {"gamma_target": 0.5, "gamma_achieved": 0.475, "pv_used": 0.8234, "n_tasks": 20, "seed": 8, "duration": 2.0, "end_anchor": false, "scenario": "v2g", "premium": 0.0, "commit": "a6af645", "milp_solver": "gurobi", "soc_step": 0.25, "pool_own": 110, "pool_union": 288, "pool_harvest": 230, "cg_converged": true, "cg_term": "priced_out", "cg_iters": 40, "cg_s": 0.43, "lp_own": 8629.0839, "lp_artificial_mass": 0.0, "lp_union": 8629.0839, "lp_check_ok": true, "start_src": "solar_bess@0", "start_obj": 8643.8, "chg_units": 60.25, "dis_units": 0.0, "chg_in_surplus_units": 20.5, "milp_s": 0.06, "milp_status": "optimal", "solver_bound": 8643.8, "artificials": 0, "feasible": true, "outcome": "feasible", "total": 8643.8, "g_units": 207.5, "trucks": 6, "batteries": 2}, {"gamma_target": 0.5, "gamma_achieved": 0.475, "pv_used": 0.8234, "n_tasks": 20, "seed": 8, "duration": 2.0, "end_anchor": false, "scenario": "v2g", "premium": 4.0, "commit": "a6af645", "milp_solver": "gurobi", "soc_step": 0.25, "pool_own": 105, "pool_union": 288, "pool_harvest": 230, "cg_converged": true, "cg_term": "priced_out", "cg_iters": 35, "cg_s": 0.39, "lp_own": 8653.6554, "lp_artificial_mass": 0.0, "lp_union": 8653.6554, "lp_check_ok": true, "start_src": "solar_bess@0", "start_obj": 8667.8, "chg_units": 60.25, "dis_units": 0.0, "chg_in_surplus_units": 20.5, "milp_s": 0.05, "milp_status": "optimal", "solver_bound": 8667.8, "artificials": 0, "feasible": true, "outcome": "feasible", "total": 8667.8, "g_units": 207.5, "trucks": 6, "batteries": 2}, {"gamma_target": 0.5, "gamma_achieved": 0.475, "pv_used": 0.8234, "n_tasks": 20, "seed": 8, "duration": 2.0, "end_anchor": false, "scenario": "v2g", "premium": 8.0, "commit": "a6af645", "milp_solver": "gurobi", "soc_step": 0.25, "pool_own": 103, "pool_union": 288, "pool_harvest": 230, "cg_converged": true, "cg_term": "priced_out", "cg_iters": 33, "cg_s": 0.37, "lp_own": 8678.1839, "lp_artificial_mass": 0.0, "lp_union": 8678.1839, "lp_check_ok": true, "start_src": "solar_bess@0", "start_obj": 8691.8, "chg_units": 60.25, "dis_units": 0.0, "chg_in_surplus_units": 20.5, "milp_s": 0.06, "milp_status": "optimal", "solver_bound": 8691.8, "artificials": 0, "feasible": true, "outcome": "feasible", "total": 8691.8, "g_units": 207.5, "trucks": 6, "batteries": 2}, {"gamma_target": 1.0, "gamma_achieved": 1.0, "pv_used": 2.5217, "n_tasks": 120, "seed": 8, "duration": 2.0, "end_anchor": false, "scenario": "solar", "premium": 0.0, "commit": "a6af645", "milp_solver": "gurobi", "soc_step": 0.25, "pool_own": 568, "pool_union": 1307, "pool_harvest": 1045, "cg_converged": true, "cg_term": "priced_out", "cg_iters": 276, "cg_s": 4.43, "lp_own": 12793.5681, "lp_artificial_mass": 0.0, "lp_union": 12793.5681, "lp_check_ok": true, "start_src": null, "start_obj": null, "chg_units": 318.5, "dis_units": 0.0, "chg_in_surplus_units": 190.0, "milp_s": 600.24, "milp_status": "feasible", "solver_bound": 12894.971741963305, "artificials": 0, "feasible": true, "outcome": "feasible", "total": 12927.96, "g_units": 280.25, "trucks": 38, "batteries": 0}, {"gamma_target": 1.0, "gamma_achieved": 1.0, "pv_used": 2.5217, "n_tasks": 120, "seed": 8, "duration": 2.0, "end_anchor": false, "scenario": "solar_bess", "premium": 0.0, "commit": "a6af645", "milp_solver": "gurobi", "soc_step": 0.25, "pool_own": 575, "pool_union": 1307, "pool_harvest": 1045, "cg_converged": true, "cg_term": "priced_out", "cg_iters": 283, "cg_s": 8.47, "lp_own": 9819.1655, "lp_artificial_mass": 0.0, "lp_union": 9819.1655, "lp_check_ok": true, "start_src": "solar@0", "start_obj": 12927.96, "chg_units": 413.75, "dis_units": 0.0, "chg_in_surplus_units": 247.75, "milp_s": 40.45, "milp_status": "optimal", "solver_bound": 9825.660672074177, "artificials": 0, "feasible": true, "outcome": "feasible", "total": 9826.5, "g_units": 196.5, "trucks": 29, "batteries": 18}, {"gamma_target": 1.0, "gamma_achieved": 1.0, "pv_used": 2.5217, "n_tasks": 120, "seed": 8, "duration": 2.0, "end_anchor": false, "scenario": "v2g_fleet", "premium": 0.0, "commit": "a6af645", "milp_solver": "gurobi", "soc_step": 0.25, "pool_own": 873, "pool_union": 2351, "pool_harvest": 1045, "cg_converged": true, "cg_term": "priced_out", "cg_iters": 581, "cg_s": 21.21, "lp_own": 10445.446, "lp_artificial_mass": 0.0, "lp_union": 10445.446, "lp_check_ok": true, "start_src": "solar_bess@0", "start_obj": 9826.5, "chg_units": 475.25, "dis_units": 0.0, "chg_in_surplus_units": 256.75, "milp_s": 600.47, "milp_status": "feasible", "solver_bound": 10597.60634924798, "artificials": 0, "feasible": true, "outcome": "feasible", "total": 11146.11, "g_units": 231.0, "trucks": 42, "batteries": 0}, {"gamma_target": 1.0, "gamma_achieved": 1.0, "pv_used": 2.5217, "n_tasks": 120, "seed": 8, "duration": 2.0, "end_anchor": false, "scenario": "v2g", "premium": 0.0, "commit": "a6af645", "milp_solver": "gurobi", "soc_step": 0.25, "pool_own": 590, "pool_union": 2351, "pool_harvest": 1045, "cg_converged": true, "cg_term": "priced_out", "cg_iters": 298, "cg_s": 11.05, "lp_own": 9562.492, "lp_artificial_mass": 0.0, "lp_union": 9562.492, "lp_check_ok": true, "start_src": "solar_bess@0", "start_obj": 9826.5, "chg_units": 420.5, "dis_units": 0.0, "chg_in_surplus_units": 247.75, "milp_s": 600.34, "milp_status": "feasible", "solver_bound": 9568.789657433812, "artificials": 0, "feasible": true, "outcome": "feasible", "total": 9575.89, "g_units": 194.5, "trucks": 30, "batteries": 12}, {"gamma_target": 1.0, "gamma_achieved": 1.0, "pv_used": 2.5217, "n_tasks": 120, "seed": 8, "duration": 2.0, "end_anchor": false, "scenario": "v2g", "premium": 4.0, "commit": "a6af645", "milp_solver": "gurobi", "soc_step": 0.25, "pool_own": 568, "pool_union": 2351, "pool_harvest": 1045, "cg_converged": true, "cg_term": "priced_out", "cg_iters": 276, "cg_s": 9.24, "lp_own": 9682.7941, "lp_artificial_mass": 0.0, "lp_union": 9682.7941, "lp_check_ok": true, "start_src": "v2g@0", "start_obj": 9695.89, "chg_units": 420.5, "dis_units": 0.0, "chg_in_surplus_units": 247.75, "milp_s": 34.27, "milp_status": "optimal", "solver_bound": 9695.832812499999, "artificials": 0, "feasible": true, "outcome": "feasible", "total": 9695.89, "g_units": 194.5, "trucks": 30, "batteries": 12}, {"gamma_target": 1.0, "gamma_achieved": 1.0, "pv_used": 2.5217, "n_tasks": 120, "seed": 8, "duration": 2.0, "end_anchor": false, "scenario": "v2g", "premium": 8.0, "commit": "a6af645", "milp_solver": "gurobi", "soc_step": 0.25, "pool_own": 582, "pool_union": 2351, "pool_harvest": 1045, "cg_converged": true, "cg_term": "priced_out", "cg_iters": 290, "cg_s": 9.99, "lp_own": 9801.2071, "lp_artificial_mass": 0.0, "lp_union": 9801.2071, "lp_check_ok": true, "start_src": "v2g@4", "start_obj": 9815.89, "chg_units": 420.5, "dis_units": 0.0, "chg_in_surplus_units": 247.75, "milp_s": 20.72, "milp_status": "optimal", "solver_bound": 9815.80249331021, "artificials": 0, "feasible": true, "outcome": "feasible", "total": 9815.89, "g_units": 194.5, "trucks": 30, "batteries": 12}, {"gamma_target": 2.0, "gamma_achieved": 2.0, "pv_used": 2.5217, "n_tasks": 60, "seed": 9, "duration": 2.0, "end_anchor": false, "scenario": "solar", "premium": 0.0, "commit": "a6af645", "milp_solver": "gurobi", "soc_step": 0.25, "pool_own": 274, "pool_union": 545, "pool_harvest": 450, "cg_converged": true, "cg_term": "priced_out", "cg_iters": 115, "cg_s": 1.02, "lp_own": 10015.9625, "lp_artificial_mass": 0.0, "lp_union": 10015.9625, "lp_check_ok": true, "start_src": null, "start_obj": null, "chg_units": 161.0, "dis_units": 0.0, "chg_in_surplus_units": 82.0, "milp_s": 0.54, "milp_status": "optimal", "solver_bound": 10044.025, "artificials": 0, "feasible": true, "outcome": "feasible", "total": 10044.02, "g_units": 228.5, "trucks": 20, "batteries": 0}, {"gamma_target": 2.0, "gamma_achieved": 2.0, "pv_used": 2.5217, "n_tasks": 60, "seed": 9, "duration": 2.0, "end_anchor": false, "scenario": "solar_bess", "premium": 0.0, "commit": "a6af645", "milp_solver": "gurobi", "soc_step": 0.25, "pool_own": 289, "pool_union": 545, "pool_harvest": 450, "cg_converged": true, "cg_term": "priced_out", "cg_iters": 130, "cg_s": 1.63, "lp_own": 3924.637, "lp_artificial_mass": 0.0, "lp_union": 3924.637, "lp_check_ok": true, "start_src": "solar@0", "start_obj": 10044.02, "chg_units": 341.75, "dis_units": 0.0, "chg_in_surplus_units": 240.0, "milp_s": 0.58, "milp_status": "optimal", "solver_bound": 3941.4375, "artificials": 0, "feasible": true, "outcome": "feasible", "total": 3941.44, "g_units": 55.0, "trucks": 16, "batteries": 28}, {"gamma_target": 2.0, "gamma_achieved": 2.0, "pv_used": 2.5217, "n_tasks": 60, "seed": 9, "duration": 2.0, "end_anchor": false, "scenario": "v2g_fleet", "premium": 0.0, "commit": "a6af645", "milp_solver": "gurobi", "soc_step": 0.25, "pool_own": 540, "pool_union": 1285, "pool_harvest": 450, "cg_converged": true, "cg_term": "priced_out", "cg_iters": 381, "cg_s": 6.74, "lp_own": 7219.7123, "lp_artificial_mass": 0.0, "lp_union": 7219.7123, "lp_check_ok": true, "start_src": "solar_bess@0", "start_obj": 3941.44, "chg_units": 278.5, "dis_units": 0.0, "chg_in_surplus_units": 173.25, "milp_s": 600.3, "milp_status": "feasible", "solver_bound": 7229.036028307599, "artificials": 0, "feasible": true, "outcome": "feasible", "total": 7374.93, "g_units": 160.5, "trucks": 21, "batteries": 0}, {"gamma_target": 2.0, "gamma_achieved": 2.0, "pv_used": 2.5217, "n_tasks": 60, "seed": 9, "duration": 2.0, "end_anchor": false, "scenario": "v2g", "premium": 0.0, "commit": "a6af645", "milp_solver": "gurobi", "soc_step": 0.25, "pool_own": 310, "pool_union": 1285, "pool_harvest": 450, "cg_converged": true, "cg_term": "priced_out", "cg_iters": 151, "cg_s": 2.41, "lp_own": 3622.0875, "lp_artificial_mass": 0.0, "lp_union": 3622.0875, "lp_check_ok": true, "start_src": "solar_bess@0", "start_obj": 3941.44, "chg_units": 347.75, "dis_units": 0.0, "chg_in_surplus_units": 242.0, "milp_s": 0.77, "milp_status": "optimal", "solver_bound": 3622.422856889506, "artificials": 0, "feasible": true, "outcome": "feasible", "total": 3622.76, "g_units": 54.0, "trucks": 17, "batteries": 19}, {"gamma_target": 2.0, "gamma_achieved": 2.0, "pv_used": 2.5217, "n_tasks": 60, "seed": 9, "duration": 2.0, "end_anchor": false, "scenario": "v2g", "premium": 4.0, "commit": "a6af645", "milp_solver": "gurobi", "soc_step": 0.25, "pool_own": 309, "pool_union": 1285, "pool_harvest": 450, "cg_converged": true, "cg_term": "priced_out", "cg_iters": 150, "cg_s": 2.34, "lp_own": 3690.3625, "lp_artificial_mass": 0.0, "lp_union": 3690.3625, "lp_check_ok": true, "start_src": "v2g@0", "start_obj": 3690.76, "chg_units": 347.75, "dis_units": 0.0, "chg_in_surplus_units": 242.0, "milp_s": 0.3, "milp_status": "optimal", "solver_bound": 3690.406066959307, "artificials": 0, "feasible": true, "outcome": "feasible", "total": 3690.76, "g_units": 54.0, "trucks": 17, "batteries": 19}, {"gamma_target": 2.0, "gamma_achieved": 2.0, "pv_used": 2.5217, "n_tasks": 60, "seed": 9, "duration": 2.0, "end_anchor": false, "scenario": "v2g", "premium": 8.0, "commit": "a6af645", "milp_solver": "gurobi", "soc_step": 0.25, "pool_own": 321, "pool_union": 1285, "pool_harvest": 450, "cg_converged": true, "cg_term": "priced_out", "cg_iters": 162, "cg_s": 2.76, "lp_own": 3758.3625, "lp_artificial_mass": 0.0, "lp_union": 3758.3625, "lp_check_ok": true, "start_src": "v2g@4", "start_obj": 3758.76, "chg_units": 347.75, "dis_units": 0.0, "chg_in_surplus_units": 242.0, "milp_s": 0.28, "milp_status": "optimal", "solver_bound": 3758.405357142859, "artificials": 0, "feasible": true, "outcome": "feasible", "total": 3758.76, "g_units": 54.0, "trucks": 17, "batteries": 19}]