[{"gamma_target": 0.25, "gamma_achieved": 0.25, "pv_used": 0.9426, "n_tasks": 60, "seed": 3, "scenario": "solar", "premium": 0.0, "commit": "0820dd8", "milp_solver": "gurobi", "soc_step": 0.25, "pool_own": 297, "pool_union": 297, "cg_converged": true, "cg_term": "priced_out", "cg_iters": 137, "cg_s": 2.41, "lp_own": 12103.3742, "lp_artificial_mass": 0.0, "lp_union": 12103.3742, "lp_check_ok": true, "start_src": null, "start_obj": null, "milp_s": 1.24, "milp_status": "optimal", "solver_bound": 12263.599999999627, "artificials": 0, "feasible": true, "outcome": "feasible", "total": 12263.6, "g_units": 286.25, "trucks": 18, "batteries": 0, "start_accepted": null}, {"gamma_target": 0.25, "gamma_achieved": 0.25, "pv_used": 0.9426, "n_tasks": 60, "seed": 3, "scenario": "v2g", "premium": 0.0, "commit": "0820dd8", "milp_solver": "gurobi", "soc_step": 0.25, "pool_own": 307, "pool_union": 584, "cg_converged": true, "cg_term": "priced_out", "cg_iters": 147, "cg_s": 4.57, "lp_own": 12095.3911, "lp_artificial_mass": 0.0, "lp_union": 12095.3911, "lp_check_ok": true, "start_src": "solar", "start_obj": 12263.6, "milp_s": 10.08, "milp_status": "optimal", "solver_bound": 12124.649815010374, "artificials": 0, "feasible": true, "outcome": "feasible", "total": 12124.65, "g_units": 283.0, "trucks": 17, "batteries": 1, "start_accepted": true}, {"gamma_target": 0.25, "gamma_achieved": 0.25, "pv_used": 0.9426, "n_tasks": 60, "seed": 3, "scenario": "v2g", "premium": 8.0, "commit": "0820dd8", "milp_solver": "gurobi", "soc_step": 0.25, "pool_own": 287, "pool_union": 584, "cg_converged": true, "cg_term": "priced_out", "cg_iters": 127, "cg_s": 3.83, "lp_own": 12232.6181, "lp_artificial_mass": 0.0, "lp_union": 12232.6181, "lp_check_ok": true, "start_src": "v2g@0", "start_obj": 12260.65, "milp_s": 33.77, "milp_status": "optimal", "solver_bound": 12260.65, "artificials": 0, "feasible": true, "outcome": "feasible", "total": 12260.65, "g_units": 283.0, "trucks": 17, "batteries": 1, "start_accepted": true}, {"gamma_target": 0.25, "gamma_achieved": 0.25, "pv_used": 0.6821, "n_tasks": 20, "seed": 4, "scenario": "solar", "premium": 0.0, "commit": "0820dd8", "milp_solver": "gurobi", "soc_step": 0.25, "pool_own": 107, "pool_union": 107, "cg_converged": true, "cg_term": "priced_out", "cg_iters": 37, "cg_s": 0.57, "lp_own": 9396.9446, "lp_artificial_mass": 0.0, "lp_union": 9396.9446, "lp_check_ok": true, "start_src": null, "start_obj": null, "milp_s": 0.05, "milp_status": "optimal", "solver_bound": 9421.2375, "artificials": 0, "feasible": true, "outcome": "feasible", "total": 9421.24, "g_units": 226.5, "trucks": 8, "batteries": 0, "start_accepted": null}, {"gamma_target": 0.25, "gamma_achieved": 0.25, "pv_used": 0.6821, "n_tasks": 20, "seed": 4, "scenario": "v2g", "premium": 0.0, "commit": "0820dd8", "milp_solver": "gurobi", "soc_step": 0.25, "pool_own": 110, "pool_union": 190, "cg_converged": true, "cg_term": "priced_out", "cg_iters": 40, "cg_s": 0.92, "lp_own": 9333.2893, "lp_artificial_mass": 0.0, "lp_union": 9333.2893, "lp_check_ok": true, "start_src": "solar", "start_obj": 9421.24, "milp_s": 0.08, "milp_status": "optimal", "solver_bound": 9343.575, "artificials": 0, "feasible": true, "outcome": "feasible", "total": 9343.58, "g_units": 225.0, "trucks": 6, "batteries": 2, "start_accepted": true}, {"gamma_target": 0.25, "gamma_achieved": 0.25, "pv_used": 0.6821, "n_tasks": 20, "seed": 4, "scenario": "v2g", "premium": 8.0, "commit": "0820dd8", "milp_solver": "gurobi", "soc_step": 0.25, "pool_own": 104, "pool_union": 190, "cg_converged": true, "cg_term": "priced_out", "cg_iters": 34, "cg_s": 0.77, "lp_own": 9381.2893, "lp_artificial_mass": 0.0, "lp_union": 9381.2893, "lp_check_ok": true, "start_src": "v2g@0", "start_obj": 9391.58, "milp_s": 0.07, "milp_status": "optimal", "solver_bound": 9391.575, "artificials": 0, "feasible": true, "outcome": "feasible", "total": 9391.58, "g_units": 225.0, "trucks": 6, "batteries": 2, "start_accepted": true}, {"gamma_target": 0.25, "gamma_achieved": 0.2458, "pv_used": 1.1767, "n_tasks": 120, "seed": 4, "scenario": "solar", "premium": 0.0, "commit": "0820dd8", "milp_solver": "gurobi", "soc_step": 0.25, "pool_own": 524, "pool_union": 524, "cg_converged": true, "cg_term": "priced_out", "cg_iters": 235, "cg_s": 6.36, "lp_own": 16963.8704, "lp_artificial_mass": 0.0, "lp_union": 16963.8704, "lp_check_ok": true, "start_src": null, "start_obj": null, "milp_s": 214.09, "milp_status": "optimal", "solver_bound": 17532.249999988824, "artificials": 0, "feasible": true, "outcome": "feasible", "total": 17532.25, "g_units": 398.75, "trucks": 35, "batteries": 0, "start_accepted": null}, {"gamma_target": 0.25, "gamma_achieved": 0.2458, "pv_used": 1.1767, "n_tasks": 120, "seed": 4, "scenario": "v2g", "premium": 0.0, "commit": "0820dd8", "milp_solver": "gurobi", "soc_step": 0.25, "pool_own": 516, "pool_union": 1001, "cg_converged": true, "cg_term": "priced_out", "cg_iters": 227, "cg_s": 11.35, "lp_own": 16957.1625, "lp_artificial_mass": 0.0, "lp_union": 16957.1625, "lp_check_ok": true, "start_src": "solar", "start_obj": 17532.25, "milp_s": 600.35, "milp_status": "feasible", "solver_bound": 16958.3355265916, "artificials": 0, "feasible": true, "outcome": "feasible", "total": 16987.34, "g_units": 390.75, "trucks": 30, "batteries": 0, "start_accepted": true}, {"gamma_target": 0.25, "gamma_achieved": 0.2458, "pv_used": 1.1767, "n_tasks": 120, "seed": 4, "scenario": "v2g", "premium": 8.0, "commit": "0820dd8", "milp_solver": "gurobi", "soc_step": 0.25, "pool_own": 519, "pool_union": 1001, "cg_converged": true, "cg_term": "priced_out", "cg_iters": 230, "cg_s": 11.27, "lp_own": 17197.1625, "lp_artificial_mass": 0.0, "lp_union": 17197.1625, "lp_check_ok": true, "start_src": "v2g@0", "start_obj": 17227.34, "milp_s": 600.31, "milp_status": "feasible", "solver_bound": 17197.323581671488, "artificials": 0, "feasible": true, "outcome": "feasible", "total": 17227.34, "g_units": 390.75, "trucks": 30, "batteries": 0, "start_accepted": true}, {"gamma_target": 0.25, "gamma_achieved": 0.25, "pv_used": 0.9426, "n_tasks": 60, "seed": 5, "scenario": "solar", "premium": 0.0, "commit": "0820dd8", "milp_solver": "gurobi", "soc_step": 0.25, "pool_own": 298, "pool_union": 298, "cg_converged": true, "cg_term": "priced_out", "cg_iters": 138, "cg_s": 2.46, "lp_own": 12154.202, "lp_artificial_mass": 0.0, "lp_union": 12154.202, "lp_check_ok": true, "start_src": null, "start_obj": null, "milp_s": 1.27, "milp_status": "optimal", "solver_bound": 12378.662499993108, "artificials": 0, "feasible": true, "outcome": "feasible", "total": 12378.66, "g_units": 288.0, "trucks": 19, "batteries": 0, "start_accepted": null}, {"gamma_target": 0.25, "gamma_achieved": 0.25, "pv_used": 0.9426, "n_tasks": 60, "seed": 5, "scenario": "v2g", "premium": 0.0, "commit": "0820dd8", "milp_solver": "gurobi", "soc_step": 0.25, "pool_own": 336, "pool_union": 649, "cg_converged": true, "cg_term": "priced_out", "cg_iters": 176, "cg_s": 6.45, "lp_own": 12094.1429, "lp_artificial_mass": 0.0, "lp_union": 12094.1429, "lp_check_ok": true, "start_src": "solar", "start_obj": 12378.66, "milp_s": 1.91, "milp_status": "optimal", "solver_bound": 12094.644078947369, "artificials": 0, "feasible": true, "outcome": "feasible", "total": 12095.01, "g_units": 282.0, "trucks": 18, "batteries": 0, "start_accepted": true}, {"gamma_target": 0.25, "gamma_achieved": 0.25, "pv_used": 0.9426, "n_tasks": 60, "seed": 5, "scenario": "v2g", "premium": 8.0, "commit": "0820dd8", "milp_solver": "gurobi", "soc_step": 0.25, "pool_own": 330, "pool_union": 649, "cg_converged": true, "cg_term": "priced_out", "cg_iters": 170, "cg_s": 6.19, "lp_own": 12238.1429, "lp_artificial_mass": 0.0, "lp_union": 12238.1429, "lp_check_ok": true, "start_src": "v2g@0", "start_obj": 12239.01, "milp_s": 0.16, "milp_status": "optimal", "solver_bound": 12238.142857142859, "artificials": 0, "feasible": true, "outcome": "feasible", "total": 12239.01, "g_units": 282.0, "trucks": 18, "batteries": 0, "start_accepted": true}, {"gamma_target": 0.25, "gamma_achieved": 0.25, "pv_used": 0.6821, "n_tasks": 20, "seed": 6, "scenario": "solar", "premium": 0.0, "commit": "0820dd8", "milp_solver": "gurobi", "soc_step": 0.25, "pool_own": 116, "pool_union": 116, "cg_converged": true, "cg_term": "priced_out", "cg_iters": 47, "cg_s": 0.7, "lp_own": 9310.1814, "lp_artificial_mass": 0.0, "lp_union": 9310.1814, "lp_check_ok": true, "start_src": null, "start_obj": null, "milp_s": 0.05, "milp_status": "optimal", "solver_bound": 9336.2, "artificials": 0, "feasible": true, "outcome": "feasible", "total": 9336.2, "g_units": 225.5, "trucks": 7, "batteries": 0, "start_accepted": null}, {"gamma_target": 0.25, "gamma_achieved": 0.25, "pv_used": 0.6821, "n_tasks": 20, "seed": 6, "scenario": "v2g", "premium": 0.0, "commit": "0820dd8", "milp_solver": "gurobi", "soc_step": 0.25, "pool_own": 116, "pool_union": 208, "cg_converged": true, "cg_term": "priced_out", "cg_iters": 47, "cg_s": 1.01, "lp_own": 9309.0821, "lp_artificial_mass": 0.0, "lp_union": 9309.0821, "lp_check_ok": true, "start_src": "solar", "start_obj": 9336.2, "milp_s": 0.14, "milp_status": "optimal", "solver_bound": 9316.271428571548, "artificials": 0, "feasible": true, "outcome": "feasible", "total": 9316.3, "g_units": 225.0, "trucks": 7, "batteries": 0, "start_accepted": true}, {"gamma_target": 0.25, "gamma_achieved": 0.25, "pv_used": 0.6821, "n_tasks": 20, "seed": 6, "scenario": "v2g", "premium": 8.0, "commit": "0820dd8", "milp_solver": "gurobi", "soc_step": 0.25, "pool_own": 111, "pool_union": 208, "cg_converged": true, "cg_term": "priced_out", "cg_iters": 42, "cg_s": 0.96, "lp_own": 9362.7964, "lp_artificial_mass": 0.0, "lp_union": 9362.7964, "lp_check_ok": true, "start_src": "v2g@0", "start_obj": 9372.3, "milp_s": 0.08, "milp_status": "optimal", "solver_bound": 9372.187500000233, "artificials": 0, "feasible": true, "outcome": "feasible", "total": 9372.3, "g_units": 225.0, "trucks": 7, "batteries": 0, "start_accepted": true}, {"gamma_target": 0.25, "gamma_achieved": 0.2458, "pv_used": 1.1767, "n_tasks": 120, "seed": 6, "scenario": "solar", "premium": 0.0, "commit": "0820dd8", "milp_solver": "gurobi", "soc_step": 0.25, "pool_own": 581, "pool_union": 581, "cg_converged": true, "cg_term": "priced_out", "cg_iters": 294, "cg_s": 8.55, "lp_own": 16948.902, "lp_artificial_mass": 0.0, "lp_union": 16948.902, "lp_check_ok": true, "start_src": null, "start_obj": null, "milp_s": 600.2, "milp_status": "feasible", "solver_bound": 17278.081815057307, "artificials": 0, "feasible": true, "outcome": "feasible", "total": 17432.22, "g_units": 396.25, "trucks": 35, "batteries": 0, "start_accepted": null}, {"gamma_target": 0.25, "gamma_achieved": 0.2458, "pv_used": 1.1767, "n_tasks": 120, "seed": 6, "scenario": "v2g", "premium": 0.0, "commit": "0820dd8", "milp_solver": "gurobi", "soc_step": 0.25, "pool_own": 561, "pool_union": 1151, "cg_converged": true, "cg_term": "priced_out", "cg_iters": 274, "cg_s": 13.5, "lp_own": 16940.9405, "lp_artificial_mass": 0.0, "lp_union": 16940.9405, "lp_check_ok": true, "start_src": "solar", "start_obj": 17432.22, "milp_s": 600.28, "milp_status": "feasible", "solver_bound": 16949.44035414296, "artificials": 0, "feasible": true, "outcome": "feasible", "total": 17037.3, "g_units": 392.0, "trucks": 30, "batteries": 0, "start_accepted": true}, {"gamma_target": 0.25, "gamma_achieved": 0.2458, "pv_used": 1.1767, "n_tasks": 120, "seed": 6, "scenario": "v2g", "premium": 8.0, "commit": "0820dd8", "milp_solver": "gurobi", "soc_step": 0.25, "pool_own": 564, "pool_union": 1151, "cg_converged": true, "cg_term": "priced_out", "cg_iters": 277, "cg_s": 13.76, "lp_own": 17179.0094, "lp_artificial_mass": 0.0, "lp_union": 17179.0094, "lp_check_ok": true, "start_src": "v2g@0", "start_obj": 17277.3, "milp_s": 600.3, "milp_status": "feasible", "solver_bound": 17184.187496371327, "artificials": 0, "feasible": true, "outcome": "feasible", "total": 17254.21, "g_units": 392.75, "trucks": 29, "batteries": 0, "start_accepted": true}, {"gamma_target": 0.25, "gamma_achieved": 0.25, "pv_used": 0.9426, "n_tasks": 60, "seed": 7, "scenario": "solar", "premium": 0.0, "commit": "0820dd8", "milp_solver": "gurobi", "soc_step": 0.25, "pool_own": 290, "pool_union": 290, "cg_converged": true, "cg_term": "priced_out", "cg_iters": 132, "cg_s": 2.3, "lp_own": 12056.4232, "lp_artificial_mass": 0.0, "lp_union": 12056.4232, "lp_check_ok": true, "start_src": null, "start_obj": null, "milp_s": 0.62, "milp_status": "optimal", "solver_bound": 12228.637499997392, "artificials": 0, "feasible": true, "outcome": "feasible", "total": 12228.64, "g_units": 286.5, "trucks": 17, "batteries": 0, "start_accepted": null}, {"gamma_target": 0.25, "gamma_achieved": 0.25, "pv_used": 0.9426, "n_tasks": 60, "seed": 7, "scenario": "v2g", "premium": 0.0, "commit": "0820dd8", "milp_solver": "gurobi", "soc_step": 0.25, "pool_own": 281, "pool_union": 547, "cg_converged": true, "cg_term": "priced_out", "cg_iters": 123, "cg_s": 3.32, "lp_own": 12056.4232, "lp_artificial_mass": 0.0, "lp_union": 12056.4232, "lp_check_ok": true, "start_src": "solar", "start_obj": 12228.64, "milp_s": 0.78, "milp_status": "optimal", "solver_bound": 12083.5625, "artificials": 0, "feasible": true, "outcome": "feasible", "total": 12083.56, "g_units": 284.0, "trucks": 16, "batteries": 0, "start_accepted": true}, {"gamma_target": 0.25, "gamma_achieved": 0.25, "pv_used": 0.9426, "n_tasks": 60, "seed": 7, "scenario": "v2g", "premium": 8.0, "commit": "0820dd8", "milp_solver": "gurobi", "soc_step": 0.25, "pool_own": 288, "pool_union": 547, "cg_converged": true, "cg_term": "priced_out", "cg_iters": 130, "cg_s": 3.55, "lp_own": 12182.1375, "lp_artificial_mass": 0.0, "lp_union": 12182.1375, "lp_check_ok": true, "start_src": "v2g@0", "start_obj": 12211.56, "milp_s": 1.66, "milp_status": "optimal", "solver_bound": 12211.562482539597, "artificials": 0, "feasible": true, "outcome": "feasible", "total": 12211.56, "g_units": 284.0, "trucks": 16, "batteries": 0, "start_accepted": true}, {"gamma_target": 0.25, "gamma_achieved": 0.25, "pv_used": 0.6821, "n_tasks": 20, "seed": 8, "scenario": "solar", "premium": 0.0, "commit": "0820dd8", "milp_solver": "gurobi", "soc_step": 0.25, "pool_own": 117, "pool_union": 117, "cg_converged": true, "cg_term": "priced_out", "cg_iters": 47, "cg_s": 0.66, "lp_own": 9344.7893, "lp_artificial_mass": 0.0, "lp_union": 9344.7893, "lp_check_ok": true, "start_src": null, "start_obj": null, "milp_s": 0.06, "milp_status": "optimal", "solver_bound": 9376.237491263, "artificials": 0, "feasible": true, "outcome": "feasible", "total": 9376.24, "g_units": 226.5, "trucks": 7, "batteries": 0, "start_accepted": null}, {"gamma_target": 0.25, "gamma_achieved": 0.25, "pv_used": 0.6821, "n_tasks": 20, "seed": 8, "scenario": "v2g", "premium": 0.0, "commit": "0820dd8", "milp_solver": "gurobi", "soc_step": 0.25, "pool_own": 110, "pool_union": 201, "cg_converged": true, "cg_term": "priced_out", "cg_iters": 40, "cg_s": 0.92, "lp_own": 9317.8518, "lp_artificial_mass": 0.0, "lp_union": 9317.8518, "lp_check_ok": true, "start_src": "solar", "start_obj": 9376.24, "milp_s": 0.08, "milp_status": "optimal", "solver_bound": 9326.744642857147, "artificials": 0, "feasible": true, "outcome": "feasible", "total": 9327.45, "g_units": 225.5, "trucks": 6, "batteries": 1, "start_accepted": true}, {"gamma_target": 0.25, "gamma_achieved": 0.25, "pv_used": 0.6821, "n_tasks": 20, "seed": 8, "scenario": "v2g", "premium": 8.0, "commit": "0820dd8", "milp_solver": "gurobi", "soc_step": 0.25, "pool_own": 102, "pool_union": 201, "cg_converged": true, "cg_term": "priced_out", "cg_iters": 32, "cg_s": 0.76, "lp_own": 9366.958, "lp_artificial_mass": 0.0, "lp_union": 9366.958, "lp_check_ok": true, "start_src": "v2g@0", "start_obj": 9375.45, "milp_s": 0.08, "milp_status": "optimal", "solver_bound": 9375.449999999999, "artificials": 0, "feasible": true, "outcome": "feasible", "total": 9375.45, "g_units": 225.5, "trucks": 6, "batteries": 1, "start_accepted": true}, {"gamma_target": 0.25, "gamma_achieved": 0.2458, "pv_used": 1.1767, "n_tasks": 120, "seed": 8, "scenario": "solar", "premium": 0.0, "commit": "0820dd8", "milp_solver": "gurobi", "soc_step": 0.25, "pool_own": 563, "pool_union": 563, "cg_converged": true, "cg_term": "priced_out", "cg_iters": 271, "cg_s": 7.79, "lp_own": 17029.9616, "lp_artificial_mass": 0.0, "lp_union": 17029.9616, "lp_check_ok": true, "start_src": null, "start_obj": null, "milp_s": 308.99, "milp_status": "optimal", "solver_bound": 17502.249999994412, "artificials": 0, "feasible": true, "outcome": "feasible", "total": 17502.25, "g_units": 398.0, "trucks": 35, "batteries": 0, "start_accepted": null}, {"gamma_target": 0.25, "gamma_achieved": 0.2458, "pv_used": 1.1767, "n_tasks": 120, "seed": 8, "scenario": "v2g", "premium": 0.0, "commit": "0820dd8", "milp_solver": "gurobi", "soc_step": 0.25, "pool_own": 546, "pool_union": 1077, "cg_converged": true, "cg_term": "priced_out", "cg_iters": 254, "cg_s": 12.97, "lp_own": 17024.2938, "lp_artificial_mass": 0.0, "lp_union": 17024.2938, "lp_check_ok": true, "start_src": "solar", "start_obj": 17502.25, "milp_s": 600.25, "milp_status": "feasible", "solver_bound": 17037.2125000094, "artificials": 0, "feasible": true, "outcome": "feasible", "total": 17088.36, "g_units": 393.25, "trucks": 30, "batteries": 0, "start_accepted": true}, {"gamma_target": 0.25, "gamma_achieved": 0.2458, "pv_used": 1.1767, "n_tasks": 120, "seed": 8, "scenario": "v2g", "premium": 8.0, "commit": "0820dd8", "milp_solver": "gurobi", "soc_step": 0.25, "pool_own": 533, "pool_union": 1077, "cg_converged": true, "cg_term": "priced_out", "cg_iters": 241, "cg_s": 11.8, "lp_own": 17268.1583, "lp_artificial_mass": 0.0, "lp_union": 17268.1583, "lp_check_ok": true, "start_src": "v2g@0", "start_obj": 17328.36, "milp_s": 600.3, "milp_status": "feasible", "solver_bound": 17277.21250002315, "artificials": 0, "feasible": true, "outcome": "feasible", "total": 17307.21, "g_units": 392.75, "trucks": 30, "batteries": 0, "start_accepted": true}, {"gamma_target": 0.25, "gamma_achieved": 0.25, "pv_used": 0.9426, "n_tasks": 60, "seed": 9, "scenario": "solar", "premium": 0.0, "commit": "0820dd8", "milp_solver": "gurobi", "soc_step": 0.25, "pool_own": 307, "pool_union": 307, "cg_converged": true, "cg_term": "priced_out", "cg_iters": 148, "cg_s": 2.63, "lp_own": 12208.0225, "lp_artificial_mass": 0.0, "lp_union": 12208.0225, "lp_check_ok": true, "start_src": null, "start_obj": null, "milp_s": 1.76, "milp_status": "optimal", "solver_bound": 12418.66249999404, "artificials": 0, "feasible": true, "outcome": "feasible", "total": 12418.66, "g_units": 291.25, "trucks": 17, "batteries": 0, "start_accepted": null}, {"gamma_target": 0.25, "gamma_achieved": 0.25, "pv_used": 0.9426, "n_tasks": 60, "seed": 9, "scenario": "v2g", "premium": 0.0, "commit": "0820dd8", "milp_solver": "gurobi", "soc_step": 0.25, "pool_own": 304, "pool_union": 633, "cg_converged": true, "cg_term": "priced_out", "cg_iters": 145, "cg_s": 4.19, "lp_own": 12126.5804, "lp_artificial_mass": 0.0, "lp_union": 12126.5804, "lp_check_ok": true, "start_src": "solar", "start_obj": 12418.66, "milp_s": 1.84, "milp_status": "optimal", "solver_bound": 12150.2625, "artificials": 0, "feasible": true, "outcome": "feasible", "total": 12150.26, "g_units": 282.5, "trucks": 18, "batteries": 1, "start_accepted": true}, {"gamma_target": 0.25, "gamma_achieved": 0.25, "pv_used": 0.9426, "n_tasks": 60, "seed": 9, "scenario": "v2g", "premium": 8.0, "commit": "0820dd8", "milp_solver": "gurobi", "soc_step": 0.25, "pool_own": 317, "pool_union": 633, "cg_converged": true, "cg_term": "priced_out", "cg_iters": 158, "cg_s": 4.97, "lp_own": 12269.5062, "lp_artificial_mass": 0.0, "lp_union": 12269.5062, "lp_check_ok": true, "start_src": "v2g@0", "start_obj": 12294.26, "milp_s": 1.0, "milp_status": "optimal", "solver_bound": 12294.2625, "artificials": 0, "feasible": true, "outcome": "feasible", "total": 12294.26, "g_units": 282.5, "trucks": 18, "batteries": 1, "start_accepted": true}]