[{"gamma_target": 0.35, "gamma_achieved": 0.3417, "pv_used": 1.0354, "n_tasks": 60, "seed": 0, "duration": 1.0, "end_anchor": true, "scenario": "solar", "premium": 0.0, "commit": "a6af645", "milp_solver": "gurobi", "soc_step": 0.25, "pool_own": 328, "pool_union": 857, "pool_harvest": 663, "cg_converged": true, "cg_term": "priced_out", "cg_iters": 174, "cg_s": 3.28, "lp_own": 11290.431, "lp_artificial_mass": 0.0, "lp_union": 11290.431, "lp_check_ok": true, "start_src": null, "start_obj": null, "chg_units": 142.0, "dis_units": 0.0, "chg_in_surplus_units": 71.0, "milp_s": 39.0, "milp_status": "optimal", "solver_bound": 11363.55, "artificials": 0, "feasible": true, "outcome": "feasible", "total": 11363.55, "g_units": 270.5, "trucks": 12, "batteries": 0}, {"gamma_target": 0.35, "gamma_achieved": 0.3417, "pv_used": 1.0354, "n_tasks": 60, "seed": 0, "duration": 1.0, "end_anchor": true, "scenario": "solar_bess", "premium": 0.0, "commit": "a6af645", "milp_solver": "gurobi", "soc_step": 0.25, "pool_own": 304, "pool_union": 857, "pool_harvest": 663, "cg_converged": true, "cg_term": "priced_out", "cg_iters": 150, "cg_s": 4.19, "lp_own": 11275.1092, "lp_artificial_mass": 0.0, "lp_union": 11275.1092, "lp_check_ok": true, "start_src": "solar@0", "start_obj": 11363.55, "chg_units": 146.25, "dis_units": 0.0, "chg_in_surplus_units": 71.0, "milp_s": 3.92, "milp_status": "optimal", "solver_bound": 11315.8125, "artificials": 0, "feasible": true, "outcome": "feasible", "total": 11315.81, "g_units": 267.5, "trucks": 12, "batteries": 2}, {"gamma_target": 0.35, "gamma_achieved": 0.3417, "pv_used": 1.0354, "n_tasks": 60, "seed": 0, "duration": 1.0, "end_anchor": true, "scenario": "v2g_fleet", "premium": 0.0, "commit": "a6af645", "milp_solver": "gurobi", "soc_step": 0.25, "pool_own": 328, "pool_union": 946, "pool_harvest": 663, "cg_converged": true, "cg_term": "priced_out", "cg_iters": 174, "cg_s": 3.56, "lp_own": 11247.1717, "lp_artificial_mass": 0.0, "lp_union": 11247.1717, "lp_check_ok": true, "start_src": "solar_bess@0", "start_obj": 11315.81, "chg_units": 147.0, "dis_units": 0.0, "chg_in_surplus_units": 71.75, "milp_s": 0.83, "milp_status": "optimal", "solver_bound": 11278.85, "artificials": 0, "feasible": true, "outcome": "feasible", "total": 11278.85, "g_units": 267.25, "trucks": 13, "batteries": 0}, {"gamma_target": 0.35, "gamma_achieved": 0.3417, "pv_used": 1.0354, "n_tasks": 60, "seed": 0, "duration": 1.0, "end_anchor": true, "scenario": "v2g", "premium": 0.0, "commit": "a6af645", "milp_solver": "gurobi", "soc_step": 0.25, "pool_own": 331, "pool_union": 946, "pool_harvest": 663, "cg_converged": true, "cg_term": "priced_out", "cg_iters": 177, "cg_s": 5.55, "lp_own": 11247.1717, "lp_artificial_mass": 0.0, "lp_union": 11247.1717, "lp_check_ok": true, "start_src": "v2g_fleet@0", "start_obj": 11278.85, "chg_units": 147.0, "dis_units": 0.0, "chg_in_surplus_units": 71.75, "milp_s": 1.16, "milp_status": "optimal", "solver_bound": 11278.849999999999, "artificials": 0, "feasible": true, "outcome": "feasible", "total": 11278.85, "g_units": 267.25, "trucks": 13, "batteries": 0}, {"gamma_target": 0.35, "gamma_achieved": 0.3417, "pv_used": 1.0354, "n_tasks": 60, "seed": 0, "duration": 1.0, "end_anchor": true, "scenario": "v2g", "premium": 8.0, "commit": "a6af645", "milp_solver": "gurobi", "soc_step": 0.25, "pool_own": 323, "pool_union": 946, "pool_harvest": 663, "cg_converged": true, "cg_term": "priced_out", "cg_iters": 169, "cg_s": 5.23, "lp_own": 11346.6429, "lp_artificial_mass": 0.0, "lp_union": 11346.6429, "lp_check_ok": true, "start_src": "v2g_fleet@0", "start_obj": 11382.85, "chg_units": 146.25, "dis_units": 0.0, "chg_in_surplus_units": 69.25, "milp_s": 1.33, "milp_status": "optimal", "solver_bound": 11375.800000000152, "artificials": 0, "feasible": true, "outcome": "feasible", "total": 11375.81, "g_units": 267.5, "trucks": 12, "batteries": 1}, {"gamma_target": 0.35, "gamma_achieved": 0.3417, "pv_used": 1.0354, "n_tasks": 60, "seed": 0, "duration": 4.0, "end_anchor": true, "scenario": "solar", "premium": 0.0, "commit": "a6af645", "milp_solver": "gurobi", "soc_step": 0.25, "pool_own": 246, "pool_union": 409, "pool_harvest": 437, "cg_converged": true, "cg_term": "priced_out", "cg_iters": 82, "cg_s": 1.43, "lp_own": 12411.3738, "lp_artificial_mass": 0.0, "lp_union": 12411.3738, "lp_check_ok": true, "start_src": null, "start_obj": null, "chg_units": 150.0, "dis_units": 0.0, "chg_in_surplus_units": 44.5, "milp_s": 0.28, "milp_status": "optimal", "solver_bound": 12438.749999996275, "artificials": 0, "feasible": true, "outcome": "feasible", "total": 12438.75, "g_units": 278.25, "trucks": 29, "batteries": 0}, {"gamma_target": 0.35, "gamma_achieved": 0.3417, "pv_used": 1.0354, "n_tasks": 60, "seed": 0, "duration": 4.0, "end_anchor": true, "scenario": "solar_bess", "premium": 0.0, "commit": "a6af645", "milp_solver": "gurobi", "soc_step": 0.25, "pool_own": 243, "pool_union": 409, "pool_harvest": 437, "cg_converged": true, "cg_term": "priced_out", "cg_iters": 79, "cg_s": 1.8, "lp_own": 12232.5232, "lp_artificial_mass": 0.0, "lp_union": 12232.5232, "lp_check_ok": true, "start_src": "solar@0", "start_obj": 12438.75, "chg_units": 158.25, "dis_units": 0.0, "chg_in_surplus_units": 46.25, "milp_s": 0.1, "milp_status": "optimal", "solver_bound": 12242.212499996647, "artificials": 0, "feasible": true, "outcome": "feasible", "total": 12242.25, "g_units": 274.0, "trucks": 26, "batteries": 3}, {"gamma_target": 0.35, "gamma_achieved": 0.3417, "pv_used": 1.0354, "n_tasks": 60, "seed": 0, "duration": 4.0, "end_anchor": true, "scenario": "v2g_fleet", "premium": 0.0, "commit": "a6af645", "milp_solver": "gurobi", "soc_step": 0.25, "pool_own": 273, "pool_union": 495, "pool_harvest": 437, "cg_converged": true, "cg_term": "priced_out", "cg_iters": 109, "cg_s": 2.18, "lp_own": 12343.175, "lp_artificial_mass": 0.0, "lp_union": 12343.175, "lp_check_ok": true, "start_src": "solar_bess@0", "start_obj": 12242.25, "chg_units": 157.75, "dis_units": 0.0, "chg_in_surplus_units": 48.25, "milp_s": 0.36, "milp_status": "optimal", "solver_bound": 12353.918750001118, "artificials": 0, "feasible": true, "outcome": "feasible", "total": 12354.19, "g_units": 277.25, "trucks": 28, "batteries": 0}, {"gamma_target": 0.35, "gamma_achieved": 0.3417, "pv_used": 1.0354, "n_tasks": 60, "seed": 0, "duration": 4.0, "end_anchor": true, "scenario": "v2g", "premium": 0.0, "commit": "a6af645", "milp_solver": "gurobi", "soc_step": 0.25, "pool_own": 238, "pool_union": 495, "pool_harvest": 437, "cg_converged": true, "cg_term": "priced_out", "cg_iters": 74, "cg_s": 1.85, "lp_own": 12232.5232, "lp_artificial_mass": 0.0, "lp_union": 12232.5232, "lp_check_ok": true, "start_src": "solar_bess@0", "start_obj": 12242.25, "chg_units": 158.25, "dis_units": 0.0, "chg_in_surplus_units": 46.25, "milp_s": 0.13, "milp_status": "optimal", "solver_bound": 12242.212499998617, "artificials": 0, "feasible": true, "outcome": "feasible", "total": 12242.25, "g_units": 274.0, "trucks": 26, "batteries": 3}, {"gamma_target": 0.35, "gamma_achieved": 0.3417, "pv_used": 1.0354, "n_tasks": 60, "seed": 0, "duration": 4.0, "end_anchor": true, "scenario": "v2g", "premium": 8.0, "commit": "a6af645", "milp_solver": "gurobi", "soc_step": 0.25, "pool_own": 240, "pool_union": 495, "pool_harvest": 437, "cg_converged": true, "cg_term": "priced_out", "cg_iters": 76, "cg_s": 1.86, "lp_own": 12440.5232, "lp_artificial_mass": 0.0, "lp_union": 12440.5232, "lp_check_ok": true, "start_src": "solar_bess@0", "start_obj": 12450.25, "chg_units": 158.25, "dis_units": 0.0, "chg_in_surplus_units": 46.25, "milp_s": 0.13, "milp_status": "optimal", "solver_bound": 12450.212499998617, "artificials": 0, "feasible": true, "outcome": "feasible", "total": 12450.25, "g_units": 274.0, "trucks": 26, "batteries": 3}, {"gamma_target": 0.35, "gamma_achieved": 0.3417, "pv_used": 1.0354, "n_tasks": 60, "seed": 1, "duration": 2.0, "end_anchor": true, "scenario": "solar", "premium": 0.0, "commit": "a6af645", "milp_solver": "gurobi", "soc_step": 0.25, "pool_own": 323, "pool_union": 761, "pool_harvest": 661, "cg_converged": true, "cg_term": "priced_out", "cg_iters": 165, "cg_s": 2.96, "lp_own": 11501.4143, "lp_artificial_mass": 0.0, "lp_union": 11501.4143, "lp_check_ok": true, "start_src": null, "start_obj": null, "chg_units": 143.0, "dis_units": 0.0, "chg_in_surplus_units": 49.25, "milp_s": 0.99, "milp_status": "optimal", "solver_bound": 11553.5625, "artificials": 0, "feasible": true, "outcome": "feasible", "total": 11553.58, "g_units": 270.75, "trucks": 16, "batteries": 0}, {"gamma_target": 0.35, "gamma_achieved": 0.3417, "pv_used": 1.0354, "n_tasks": 60, "seed": 1, "duration": 2.0, "end_anchor": true, "scenario": "solar_bess", "premium": 0.0, "commit": "a6af645", "milp_solver": "gurobi", "soc_step": 0.25, "pool_own": 307, "pool_union": 761, "pool_harvest": 661, "cg_converged": true, "cg_term": "priced_out", "cg_iters": 149, "cg_s": 4.13, "lp_own": 11492.7339, "lp_artificial_mass": 0.0, "lp_union": 11492.7339, "lp_check_ok": true, "start_src": "solar@0", "start_obj": 11553.58, "chg_units": 144.75, "dis_units": 0.0, "chg_in_surplus_units": 47.25, "milp_s": 0.31, "milp_status": "optimal", "solver_bound": 11519.662500000004, "artificials": 0, "feasible": true, "outcome": "feasible", "total": 11519.69, "g_units": 269.0, "trucks": 16, "batteries": 1}, {"gamma_target": 0.35, "gamma_achieved": 0.3417, "pv_used": 1.0354, "n_tasks": 60, "seed": 1, "duration": 2.0, "end_anchor": true, "scenario": "v2g_fleet", "premium": 0.0, "commit": "a6af645", "milp_solver": "gurobi", "soc_step": 0.25, "pool_own": 349, "pool_union": 858, "pool_harvest": 661, "cg_converged": true, "cg_term": "priced_out", "cg_iters": 191, "cg_s": 3.87, "lp_own": 11496.4464, "lp_artificial_mass": 0.0, "lp_union": 11496.4464, "lp_check_ok": true, "start_src": "solar_bess@0", "start_obj": 11519.69, "chg_units": 152.75, "dis_units": 0.0, "chg_in_surplus_units": 55.25, "milp_s": 1.34, "milp_status": "optimal", "solver_bound": 11538.900000000001, "artificials": 0, "feasible": true, "outcome": "feasible", "total": 11539.09, "g_units": 269.25, "trucks": 17, "batteries": 0}, {"gamma_target": 0.35, "gamma_achieved": 0.3417, "pv_used": 1.0354, "n_tasks": 60, "seed": 1, "duration": 2.0, "end_anchor": true, "scenario": "v2g", "premium": 0.0, "commit": "a6af645", "milp_solver": "gurobi", "soc_step": 0.25, "pool_own": 313, "pool_union": 858, "pool_harvest": 661, "cg_converged": true, "cg_term": "priced_out", "cg_iters": 155, "cg_s": 4.58, "lp_own": 11492.7339, "lp_artificial_mass": 0.0, "lp_union": 11492.7339, "lp_check_ok": true, "start_src": "solar_bess@0", "start_obj": 11519.69, "chg_units": 144.75, "dis_units": 0.0, "chg_in_surplus_units": 47.25, "milp_s": 0.34, "milp_status": "optimal", "solver_bound": 11519.6625, "artificials": 0, "feasible": true, "outcome": "feasible", "total": 11519.69, "g_units": 269.0, "trucks": 16, "batteries": 1}, {"gamma_target": 0.35, "gamma_achieved": 0.3417, "pv_used": 1.0354, "n_tasks": 60, "seed": 1, "duration": 2.0, "end_anchor": true, "scenario": "v2g", "premium": 8.0, "commit": "a6af645", "milp_solver": "gurobi", "soc_step": 0.25, "pool_own": 298, "pool_union": 858, "pool_harvest": 661, "cg_converged": true, "cg_term": "priced_out", "cg_iters": 140, "cg_s": 4.1, "lp_own": 11618.1893, "lp_artificial_mass": 0.0, "lp_union": 11618.1893, "lp_check_ok": true, "start_src": "solar_bess@0", "start_obj": 11647.69, "chg_units": 144.75, "dis_units": 0.0, "chg_in_surplus_units": 47.25, "milp_s": 0.41, "milp_status": "optimal", "solver_bound": 11647.662500000006, "artificials": 0, "feasible": true, "outcome": "feasible", "total": 11647.69, "g_units": 269.0, "trucks": 16, "batteries": 1}, {"gamma_target": 0.35, "gamma_achieved": 0.3417, "pv_used": 1.0354, "n_tasks": 60, "seed": 2, "duration": 1.0, "end_anchor": true, "scenario": "solar", "premium": 0.0, "commit": "a6af645", "milp_solver": "gurobi", "soc_step": 0.25, "pool_own": 332, "pool_union": 971, "pool_harvest": 742, "cg_converged": true, "cg_term": "priced_out", "cg_iters": 178, "cg_s": 3.23, "lp_own": 11203.5293, "lp_artificial_mass": 0.0, "lp_union": 11203.5293, "lp_check_ok": true, "start_src": null, "start_obj": null, "chg_units": 141.0, "dis_units": 0.0, "chg_in_surplus_units": 61.0, "milp_s": 22.41, "milp_status": "optimal", "solver_bound": 11268.525, "artificials": 0, "feasible": true, "outcome": "feasible", "total": 11268.52, "g_units": 269.25, "trucks": 11, "batteries": 0}, {"gamma_target": 0.35, "gamma_achieved": 0.3417, "pv_used": 1.0354, "n_tasks": 60, "seed": 2, "duration": 1.0, "end_anchor": true, "scenario": "solar_bess", "premium": 0.0, "commit": "a6af645", "milp_solver": "gurobi", "soc_step": 0.25, "pool_own": 323, "pool_union": 971, "pool_harvest": 742, "cg_converged": true, "cg_term": "priced_out", "cg_iters": 169, "cg_s": 4.95, "lp_own": 11203.5293, "lp_artificial_mass": 0.0, "lp_union": 11203.5293, "lp_check_ok": true, "start_src": "solar@0", "start_obj": 11268.52, "chg_units": 142.75, "dis_units": 0.0, "chg_in_surplus_units": 62.25, "milp_s": 4.62, "milp_status": "optimal", "solver_bound": 11234.6375, "artificials": 0, "feasible": true, "outcome": "feasible", "total": 11234.64, "g_units": 267.5, "trucks": 11, "batteries": 1}, {"gamma_target": 0.35, "gamma_achieved": 0.3417, "pv_used": 1.0354, "n_tasks": 60, "seed": 2, "duration": 1.0, "end_anchor": true, "scenario": "v2g_fleet", "premium": 0.0, "commit": "a6af645", "milp_solver": "gurobi", "soc_step": 0.25, "pool_own": 355, "pool_union": 1063, "pool_harvest": 742, "cg_converged": true, "cg_term": "priced_out", "cg_iters": 201, "cg_s": 4.07, "lp_own": 11185.4881, "lp_artificial_mass": 0.0, "lp_union": 11185.4881, "lp_check_ok": true, "start_src": "solar_bess@0", "start_obj": 11234.64, "chg_units": 150.5, "dis_units": 0.0, "chg_in_surplus_units": 66.5, "milp_s": 3.36, "milp_status": "optimal", "solver_bound": 11224.025, "artificials": 0, "feasible": true, "outcome": "feasible", "total": 11224.02, "g_units": 267.0, "trucks": 12, "batteries": 0}, {"gamma_target": 0.35, "gamma_achieved": 0.3417, "pv_used": 1.0354, "n_tasks": 60, "seed": 2, "duration": 1.0, "end_anchor": true, "scenario": "v2g", "premium": 0.0, "commit": "a6af645", "milp_solver": "gurobi", "soc_step": 0.25, "pool_own": 356, "pool_union": 1063, "pool_harvest": 742, "cg_converged": true, "cg_term": "priced_out", "cg_iters": 202, "cg_s": 6.71, "lp_own": 11185.4881, "lp_artificial_mass": 0.0, "lp_union": 11185.4881, "lp_check_ok": true, "start_src": "v2g_fleet@0", "start_obj": 11224.02, "chg_units": 144.5, "dis_units": 0.0, "chg_in_surplus_units": 67.5, "milp_s": 3.4, "milp_status": "optimal", "solver_bound": 11214.724997024794, "artificials": 0, "feasible": true, "outcome": "feasible", "total": 11214.72, "g_units": 267.0, "trucks": 11, "batteries": 1}, {"gamma_target": 0.35, "gamma_achieved": 0.3417, "pv_used": 1.0354, "n_tasks": 60, "seed": 2, "duration": 1.0, "end_anchor": true, "scenario": "v2g", "premium": 8.0, "commit": "a6af645", "milp_solver": "gurobi", "soc_step": 0.25, "pool_own": 347, "pool_union": 1063, "pool_harvest": 742, "cg_converged": true, "cg_term": "priced_out", "cg_iters": 193, "cg_s": 6.26, "lp_own": 11274.25, "lp_artificial_mass": 0.0, "lp_union": 11274.25, "lp_check_ok": true, "start_src": "v2g@0", "start_obj": 11302.72, "chg_units": 144.5, "dis_units": 0.0, "chg_in_surplus_units": 67.5, "milp_s": 2.59, "milp_status": "optimal", "solver_bound": 11302.724983195634, "artificials": 0, "feasible": true, "outcome": "feasible", "total": 11302.72, "g_units": 267.0, "trucks": 11, "batteries": 1}, {"gamma_target": 0.35, "gamma_achieved": 0.3417, "pv_used": 1.0354, "n_tasks": 60, "seed": 2, "duration": 4.0, "end_anchor": true, "scenario": "solar", "premium": 0.0, "commit": "a6af645", "milp_solver": "gurobi", "soc_step": 0.25, "pool_own": 284, "pool_union": 449, "pool_harvest": 396, "cg_converged": true, "cg_term": "priced_out", "cg_iters": 121, "cg_s": 2.08, "lp_own": 12101.5875, "lp_artificial_mass": 0.0, "lp_union": 12101.5875, "lp_check_ok": true, "start_src": null, "start_obj": null, "chg_units": 149.5, "dis_units": 0.0, "chg_in_surplus_units": 43.75, "milp_s": 0.7, "milp_status": "optimal", "solver_bound": 12188.7375, "artificials": 0, "feasible": true, "outcome": "feasible", "total": 12188.74, "g_units": 278.75, "trucks": 23, "batteries": 0}, {"gamma_target": 0.35, "gamma_achieved": 0.3417, "pv_used": 1.0354, "n_tasks": 60, "seed": 2, "duration": 4.0, "end_anchor": true, "scenario": "solar_bess", "premium": 0.0, "commit": "a6af645", "milp_solver": "gurobi", "soc_step": 0.25, "pool_own": 234, "pool_union": 449, "pool_harvest": 396, "cg_converged": true, "cg_term": "priced_out", "cg_iters": 71, "cg_s": 1.56, "lp_own": 11840.4424, "lp_artificial_mass": 0.0, "lp_union": 11840.4424, "lp_check_ok": true, "start_src": "solar@0", "start_obj": 12188.74, "chg_units": 178.25, "dis_units": 0.0, "chg_in_surplus_units": 44.25, "milp_s": 0.38, "milp_status": "optimal", "solver_bound": 11864.3024999997, "artificials": 0, "feasible": true, "outcome": "feasible", "total": 11865.35, "g_units": 269.5, "trucks": 20, "batteries": 5}, {"gamma_target": 0.35, "gamma_achieved": 0.3417, "pv_used": 1.0354, "n_tasks": 60, "seed": 2, "duration": 4.0, "end_anchor": true, "scenario": "v2g_fleet", "premium": 0.0, "commit": "a6af645", "milp_solver": "gurobi", "soc_step": 0.25, "pool_own": 410, "pool_union": 730, "pool_harvest": 396, "cg_converged": true, "cg_term": "priced_out", "cg_iters": 247, "cg_s": 5.63, "lp_own": 11850.8361, "lp_artificial_mass": 0.0, "lp_union": 11850.8361, "lp_check_ok": true, "start_src": "solar_bess@0", "start_obj": 11865.35, "chg_units": 193.75, "dis_units": 0.0, "chg_in_surplus_units": 50.75, "milp_s": 12.65, "milp_status": "optimal", "solver_bound": 11931.087499999998, "artificials": 0, "feasible": true, "outcome": "feasible", "total": 11931.09, "g_units": 272.25, "trucks": 23, "batteries": 0}, {"gamma_target": 0.35, "gamma_achieved": 0.3417, "pv_used": 1.0354, "n_tasks": 60, "seed": 2, "duration": 4.0, "end_anchor": true, "scenario": "v2g", "premium": 0.0, "commit": "a6af645", "milp_solver": "gurobi", "soc_step": 0.25, "pool_own": 245, "pool_union": 730, "pool_harvest": 396, "cg_converged": true, "cg_term": "priced_out", "cg_iters": 82, "cg_s": 2.01, "lp_own": 11818.2, "lp_artificial_mass": 0.0, "lp_union": 11818.2, "lp_check_ok": true, "start_src": "solar_bess@0", "start_obj": 11865.35, "chg_units": 178.0, "dis_units": 0.0, "chg_in_surplus_units": 44.5, "milp_s": 0.6, "milp_status": "optimal", "solver_bound": 11828.349999999999, "artificials": 0, "feasible": true, "outcome": "feasible", "total": 11828.35, "g_units": 269.25, "trucks": 21, "batteries": 3}, {"gamma_target": 0.35, "gamma_achieved": 0.3417, "pv_used": 1.0354, "n_tasks": 60, "seed": 2, "duration": 4.0, "end_anchor": true, "scenario": "v2g", "premium": 8.0, "commit": "a6af645", "milp_solver": "gurobi", "soc_step": 0.25, "pool_own": 243, "pool_union": 730, "pool_harvest": 396, "cg_converged": true, "cg_term": "priced_out", "cg_iters": 80, "cg_s": 1.94, "lp_own": 11985.7576, "lp_artificial_mass": 0.0, "lp_union": 11985.7576, "lp_check_ok": true, "start_src": "v2g@0", "start_obj": 11996.35, "chg_units": 178.0, "dis_units": 0.0, "chg_in_surplus_units": 44.5, "milp_s": 1.33, "milp_status": "optimal", "solver_bound": 11996.349999999999, "artificials": 0, "feasible": true, "outcome": "feasible", "total": 11996.35, "g_units": 269.25, "trucks": 21, "batteries": 3}, {"gamma_target": 0.35, "gamma_achieved": 0.3417, "pv_used": 1.0354, "n_tasks": 60, "seed": 3, "duration": 2.0, "end_anchor": true, "scenario": "solar", "premium": 0.0, "commit": "a6af645", "milp_solver": "gurobi", "soc_step": 0.25, "pool_own": 303, "pool_union": 710, "pool_harvest": 583, "cg_converged": true, "cg_term": "priced_out", "cg_iters": 143, "cg_s": 2.51, "lp_own": 11580.9256, "lp_artificial_mass": 0.0, "lp_union": 11580.9256, "lp_check_ok": true, "start_src": null, "start_obj": null, "chg_units": 143.5, "dis_units": 0.0, "chg_in_surplus_units": 51.25, "milp_s": 2.0, "milp_status": "optimal", "solver_bound": 11648.576250000002, "artificials": 0, "feasible": true, "outcome": "feasible", "total": 11648.59, "g_units": 272.0, "trucks": 17, "batteries": 0}, {"gamma_target": 0.35, "gamma_achieved": 0.3417, "pv_used": 1.0354, "n_tasks": 60, "seed": 3, "duration": 2.0, "end_anchor": true, "scenario": "solar_bess", "premium": 0.0, "commit": "a6af645", "milp_solver": "gurobi", "soc_step": 0.25, "pool_own": 305, "pool_union": 710, "pool_harvest": 583, "cg_converged": true, "cg_term": "priced_out", "cg_iters": 145, "cg_s": 4.2, "lp_own": 11557.8088, "lp_artificial_mass": 0.0, "lp_union": 11557.8088, "lp_check_ok": true, "start_src": "solar@0", "start_obj": 11648.59, "chg_units": 148.25, "dis_units": 0.0, "chg_in_surplus_units": 52.5, "milp_s": 0.78, "milp_status": "optimal", "solver_bound": 11584.8625, "artificials": 0, "feasible": true, "outcome": "feasible", "total": 11584.86, "g_units": 269.5, "trucks": 17, "batteries": 1}, {"gamma_target": 0.35, "gamma_achieved": 0.3417, "pv_used": 1.0354, "n_tasks": 60, "seed": 3, "duration": 2.0, "end_anchor": true, "scenario": "v2g_fleet", "premium": 0.0, "commit": "a6af645", "milp_solver": "gurobi", "soc_step": 0.25, "pool_own": 304, "pool_union": 832, "pool_harvest": 583, "cg_converged": true, "cg_term": "priced_out", "cg_iters": 144, "cg_s": 2.8, "lp_own": 11559.4732, "lp_artificial_mass": 0.0, "lp_union": 11559.4732, "lp_check_ok": true, "start_src": "solar_bess@0", "start_obj": 11584.86, "chg_units": 148.5, "dis_units": 0.0, "chg_in_surplus_units": 58.5, "milp_s": 0.68, "milp_status": "optimal", "solver_bound": 11588.85, "artificials": 0, "feasible": true, "outcome": "feasible", "total": 11588.85, "g_units": 270.5, "trucks": 17, "batteries": 0}, {"gamma_target": 0.35, "gamma_achieved": 0.3417, "pv_used": 1.0354, "n_tasks": 60, "seed": 3, "duration": 2.0, "end_anchor": true, "scenario": "v2g", "premium": 0.0, "commit": "a6af645", "milp_solver": "gurobi", "soc_step": 0.25, "pool_own": 313, "pool_union": 832, "pool_harvest": 583, "cg_converged": true, "cg_term": "priced_out", "cg_iters": 153, "cg_s": 4.83, "lp_own": 11556.2375, "lp_artificial_mass": 0.0, "lp_union": 11556.2375, "lp_check_ok": true, "start_src": "solar_bess@0", "start_obj": 11584.86, "chg_units": 148.25, "dis_units": 0.0, "chg_in_surplus_units": 52.5, "milp_s": 0.39, "milp_status": "optimal", "solver_bound": 11584.8625, "artificials": 0, "feasible": true, "outcome": "feasible", "total": 11584.86, "g_units": 269.5, "trucks": 17, "batteries": 1}, {"gamma_target": 0.35, "gamma_achieved": 0.3417, "pv_used": 1.0354, "n_tasks": 60, "seed": 3, "duration": 2.0, "end_anchor": true, "scenario": "v2g", "premium": 8.0, "commit": "a6af645", "milp_solver": "gurobi", "soc_step": 0.25, "pool_own": 302, "pool_union": 832, "pool_harvest": 583, "cg_converged": true, "cg_term": "priced_out", "cg_iters": 142, "cg_s": 4.41, "lp_own": 11693.4395, "lp_artificial_mass": 0.0, "lp_union": 11693.4395, "lp_check_ok": true, "start_src": "solar_bess@0", "start_obj": 11720.86, "chg_units": 148.25, "dis_units": 0.0, "chg_in_surplus_units": 52.5, "milp_s": 0.45, "milp_status": "optimal", "solver_bound": 11719.879263404277, "artificials": 0, "feasible": true, "outcome": "feasible", "total": 11720.86, "g_units": 269.5, "trucks": 17, "batteries": 1}, {"gamma_target": 0.35, "gamma_achieved": 0.3417, "pv_used": 1.0354, "n_tasks": 60, "seed": 4, "duration": 1.0, "end_anchor": true, "scenario": "solar", "premium": 0.0, "commit": "a6af645", "milp_solver": "gurobi", "soc_step": 0.25, "pool_own": 297, "pool_union": 820, "pool_harvest": 677, "cg_converged": true, "cg_term": "priced_out", "cg_iters": 143, "cg_s": 2.5, "lp_own": 11535.6893, "lp_artificial_mass": 0.0, "lp_union": 11535.6893, "lp_check_ok": true, "start_src": null, "start_obj": null, "chg_units": 142.0, "dis_units": 0.0, "chg_in_surplus_units": 54.75, "milp_s": 3.45, "milp_status": "optimal", "solver_bound": 11578.55, "artificials": 0, "feasible": true, "outcome": "feasible", "total": 11578.55, "g_units": 270.25, "trucks": 17, "batteries": 0}, {"gamma_target": 0.35, "gamma_achieved": 0.3417, "pv_used": 1.0354, "n_tasks": 60, "seed": 4, "duration": 1.0, "end_anchor": true, "scenario": "solar_bess", "premium": 0.0, "commit": "a6af645", "milp_solver": "gurobi", "soc_step": 0.25, "pool_own": 303, "pool_union": 820, "pool_harvest": 677, "cg_converged": true, "cg_term": "priced_out", "cg_iters": 149, "cg_s": 4.06, "lp_own": 11467.151, "lp_artificial_mass": 0.0, "lp_union": 11467.151, "lp_check_ok": true, "start_src": "solar@0", "start_obj": 11578.55, "chg_units": 149.0, "dis_units": 0.0, "chg_in_surplus_units": 68.5, "milp_s": 18.94, "milp_status": "optimal", "solver_bound": 11506.924980025, "artificials": 0, "feasible": true, "outcome": "feasible", "total": 11506.92, "g_units": 268.0, "trucks": 15, "batteries": 3}, {"gamma_target": 0.35, "gamma_achieved": 0.3417, "pv_used": 1.0354, "n_tasks": 60, "seed": 4, "duration": 1.0, "end_anchor": true, "scenario": "v2g_fleet", "premium": 0.0, "commit": "a6af645", "milp_solver": "gurobi", "soc_step": 0.25, "pool_own": 318, "pool_union": 904, "pool_harvest": 677, "cg_converged": true, "cg_term": "priced_out", "cg_iters": 164, "cg_s": 3.22, "lp_own": 11461.8321, "lp_artificial_mass": 0.0, "lp_union": 11461.8321, "lp_check_ok": true, "start_src": "solar_bess@0", "start_obj": 11506.92, "chg_units": 150.5, "dis_units": 0.0, "chg_in_surplus_units": 70.0, "milp_s": 1.07, "milp_status": "optimal", "solver_bound": 11469.025, "artificials": 0, "feasible": true, "outcome": "feasible", "total": 11469.03, "g_units": 267.5, "trucks": 17, "batteries": 0}, {"gamma_target": 0.35, "gamma_achieved": 0.3417, "pv_used": 1.0354, "n_tasks": 60, "seed": 4, "duration": 1.0, "end_anchor": true, "scenario": "v2g", "premium": 0.0, "commit": "a6af645", "milp_solver": "gurobi", "soc_step": 0.25, "pool_own": 330, "pool_union": 904, "pool_harvest": 677, "cg_converged": true, "cg_term": "priced_out", "cg_iters": 176, "cg_s": 5.57, "lp_own": 11450.2607, "lp_artificial_mass": 0.0, "lp_union": 11450.2607, "lp_check_ok": true, "start_src": "v2g_fleet@0", "start_obj": 11469.03, "chg_units": 150.75, "dis_units": 0.0, "chg_in_surplus_units": 66.75, "milp_s": 0.61, "milp_status": "optimal", "solver_bound": 11459.950000000004, "artificials": 0, "feasible": true, "outcome": "feasible", "total": 11460.04, "g_units": 267.5, "trucks": 16, "batteries": 1}, {"gamma_target": 0.35, "gamma_achieved": 0.3417, "pv_used": 1.0354, "n_tasks": 60, "seed": 4, "duration": 1.0, "end_anchor": true, "scenario": "v2g", "premium": 8.0, "commit": "a6af645", "milp_solver": "gurobi", "soc_step": 0.25, "pool_own": 327, "pool_union": 904, "pool_harvest": 677, "cg_converged": true, "cg_term": "priced_out", "cg_iters": 173, "cg_s": 5.24, "lp_own": 11574.6149, "lp_artificial_mass": 0.0, "lp_union": 11574.6149, "lp_check_ok": true, "start_src": "v2g@0", "start_obj": 11588.04, "chg_units": 149.75, "dis_units": 0.0, "chg_in_surplus_units": 60.5, "milp_s": 0.77, "milp_status": "optimal", "solver_bound": 11587.875000000404, "artificials": 0, "feasible": true, "outcome": "feasible", "total": 11587.99, "g_units": 267.5, "trucks": 16, "batteries": 1}, {"gamma_target": 0.35, "gamma_achieved": 0.3417, "pv_used": 1.0354, "n_tasks": 60, "seed": 4, "duration": 4.0, "end_anchor": true, "scenario": "solar", "premium": 0.0, "commit": "a6af645", "milp_solver": "gurobi", "soc_step": 0.25, "pool_own": 236, "pool_union": 389, "pool_harvest": 431, "cg_converged": true, "cg_term": "priced_out", "cg_iters": 72, "cg_s": 1.3, "lp_own": 12385.6048, "lp_artificial_mass": 0.0, "lp_union": 12385.6048, "lp_check_ok": true, "start_src": null, "start_obj": null, "chg_units": 150.5, "dis_units": 0.0, "chg_in_surplus_units": 48.75, "milp_s": 0.17, "milp_status": "optimal", "solver_bound": 12403.751785710454, "artificials": 0, "feasible": true, "outcome": "feasible", "total": 12403.76, "g_units": 278.5, "trucks": 28, "batteries": 0}, {"gamma_target": 0.35, "gamma_achieved": 0.3417, "pv_used": 1.0354, "n_tasks": 60, "seed": 4, "duration": 4.0, "end_anchor": true, "scenario": "solar_bess", "premium": 0.0, "commit": "a6af645", "milp_solver": "gurobi", "soc_step": 0.25, "pool_own": 238, "pool_union": 389, "pool_harvest": 431, "cg_converged": true, "cg_term": "priced_out", "cg_iters": 74, "cg_s": 1.7, "lp_own": 12236.4857, "lp_artificial_mass": 0.0, "lp_union": 12236.4857, "lp_check_ok": true, "start_src": "solar@0", "start_obj": 12403.76, "chg_units": 158.25, "dis_units": 0.0, "chg_in_surplus_units": 50.0, "milp_s": 0.1, "milp_status": "optimal", "solver_bound": 12246.175000000745, "artificials": 0, "feasible": true, "outcome": "feasible", "total": 12246.22, "g_units": 275.0, "trucks": 26, "batteries": 2}, {"gamma_target": 0.35, "gamma_achieved": 0.3417, "pv_used": 1.0354, "n_tasks": 60, "seed": 4, "duration": 4.0, "end_anchor": true, "scenario": "v2g_fleet", "premium": 0.0, "commit": "a6af645", "milp_solver": "gurobi", "soc_step": 0.25, "pool_own": 274, "pool_union": 479, "pool_harvest": 431, "cg_converged": true, "cg_term": "priced_out", "cg_iters": 110, "cg_s": 2.25, "lp_own": 12302.5625, "lp_artificial_mass": 0.0, "lp_union": 12302.5625, "lp_check_ok": true, "start_src": "solar_bess@0", "start_obj": 12246.22, "chg_units": 154.25, "dis_units": 0.0, "chg_in_surplus_units": 50.5, "milp_s": 0.19, "milp_status": "optimal", "solver_bound": 12303.985344836488, "artificials": 0, "feasible": true, "outcome": "feasible", "total": 12304.0, "g_units": 276.0, "trucks": 28, "batteries": 0}, {"gamma_target": 0.35, "gamma_achieved": 0.3417, "pv_used": 1.0354, "n_tasks": 60, "seed": 4, "duration": 4.0, "end_anchor": true, "scenario": "v2g", "premium": 0.0, "commit": "a6af645", "milp_solver": "gurobi", "soc_step": 0.25, "pool_own": 239, "pool_union": 479, "pool_harvest": 431, "cg_converged": true, "cg_term": "priced_out", "cg_iters": 75, "cg_s": 1.91, "lp_own": 12236.4857, "lp_artificial_mass": 0.0, "lp_union": 12236.4857, "lp_check_ok": true, "start_src": "solar_bess@0", "start_obj": 12246.22, "chg_units": 158.25, "dis_units": 0.0, "chg_in_surplus_units": 50.0, "milp_s": 0.13, "milp_status": "optimal", "solver_bound": 12246.17499999899, "artificials": 0, "feasible": true, "outcome": "feasible", "total": 12246.23, "g_units": 275.0, "trucks": 26, "batteries": 2}, {"gamma_target": 0.35, "gamma_achieved": 0.3417, "pv_used": 1.0354, "n_tasks": 60, "seed": 4, "duration": 4.0, "end_anchor": true, "scenario": "v2g", "premium": 8.0, "commit": "a6af645", "milp_solver": "gurobi", "soc_step": 0.25, "pool_own": 237, "pool_union": 479, "pool_harvest": 431, "cg_converged": true, "cg_term": "priced_out", "cg_iters": 73, "cg_s": 1.84, "lp_own": 12444.4857, "lp_artificial_mass": 0.0, "lp_union": 12444.4857, "lp_check_ok": true, "start_src": "solar_bess@0", "start_obj": 12454.22, "chg_units": 157.5, "dis_units": 0.0, "chg_in_surplus_units": 47.5, "milp_s": 0.13, "milp_status": "optimal", "solver_bound": 12454.175000002608, "artificials": 0, "feasible": true, "outcome": "feasible", "total": 12454.19, "g_units": 275.0, "trucks": 26, "batteries": 2}]